{"cityId":32,"groups":[{"groupId":1,"group":"Продукты питания","groupName":"food","turnover":14450000000,"turnoverChange":-0.013000000000000001,"share":0.1675,"margin":1.68,"competition":1,"priceLevel":67.43,"products":[{"productId":90,"product":"Вино","productName":"wine","volume":336670000,"volumeChange":0.015,"amount":188126,"amountChange":0.012,"priceLevel":63.24,"sellers":21,"sellersChange":2,"divisions":201,"divisionsChange":16,"competition":2,"price":1790,"priceChange":17.11,"quality":18.52,"qualityChange":-0.09},{"productId":251,"product":"Виноград","productName":"grape","volume":409280000,"volumeChange":-0.05,"amount":1451290,"amountChange":-0.057,"priceLevel":69.69,"sellers":22,"sellersChange":0,"divisions":209,"divisionsChange":0,"competition":2,"price":283,"priceChange":3.29,"quality":18.9,"qualityChange":0.01},{"productId":84,"product":"Йогурт","productName":"yogurt","volume":352860000,"volumeChange":-0.069,"amount":1237186,"amountChange":-0.065,"priceLevel":52.6,"sellers":13,"sellersChange":0,"divisions":156,"divisionsChange":0,"competition":1,"price":285,"priceChange":-1.12,"quality":16.83,"qualityChange":0.08},{"productId":255,"product":"Картофель","productName":"potato","volume":533190000.00000006,"volumeChange":-0.083,"amount":5603216,"amountChange":-0.073,"priceLevel":100,"sellers":14,"sellersChange":1,"divisions":158,"divisionsChange":15,"competition":1,"price":95.03,"priceChange":-1.28,"quality":18.33,"qualityChange":-0.08},{"productId":78,"product":"Колбаса","productName":"sausages","volume":421980000,"volumeChange":-0.07400000000000001,"amount":243415,"amountChange":-0.063,"priceLevel":60.42,"sellers":19,"sellersChange":1,"divisions":178,"divisionsChange":16,"competition":2,"price":1729,"priceChange":-23.63,"quality":16.04,"qualityChange":-0.09},{"productId":92,"product":"Крепкий алкоголь","productName":"vodka","volume":287250000,"volumeChange":0.18899999999999997,"amount":43546,"amountChange":0.182,"priceLevel":66.56,"sellers":17,"sellersChange":3,"divisions":208,"divisionsChange":37,"competition":2,"price":6625,"priceChange":69.59,"quality":19.08,"qualityChange":0.14},{"productId":87,"product":"Крупа","productName":"croup","volume":411440000,"volumeChange":-0.040999999999999995,"amount":4627745,"amountChange":-0.057999999999999996,"priceLevel":27.92,"sellers":12,"sellersChange":0,"divisions":148,"divisionsChange":0,"competition":1,"price":89.04,"priceChange":0.82,"quality":17.38,"qualityChange":0.01},{"productId":80,"product":"Макаронные изделия","productName":"macaron","volume":496740000,"volumeChange":-0.053,"amount":2572660,"amountChange":-0.05,"priceLevel":70.45,"sellers":15,"sellersChange":0,"divisions":114,"divisionsChange":0,"competition":1,"price":193,"priceChange":-0.43,"quality":18.24,"qualityChange":-0.05},{"productId":238,"product":"Масло","productName":"butter","volume":498370000,"volumeChange":-0.045,"amount":653340,"amountChange":-0.040999999999999995,"priceLevel":52.33,"sellers":12,"sellersChange":-1,"divisions":156,"divisionsChange":-8,"competition":1,"price":762,"priceChange":-3.57,"quality":17.68,"qualityChange":0.11},{"productId":49,"product":"Молоко","productName":"milk","volume":635430000,"volumeChange":-0.055999999999999994,"amount":3688679,"amountChange":-0.057999999999999996,"priceLevel":70.02,"sellers":16,"sellersChange":1,"divisions":200,"divisionsChange":11,"competition":1,"price":173,"priceChange":0.2,"quality":16.53,"qualityChange":0.01},{"productId":440,"product":"Морковь","productName":"carrot","volume":549500000,"volumeChange":-0.043,"amount":4914848,"amountChange":-0.032,"priceLevel":99.96,"sellers":14,"sellersChange":0,"divisions":159,"divisionsChange":0,"competition":1,"price":112,"priceChange":-1.47,"quality":20.88,"qualityChange":-0.22},{"productId":86,"product":"Мука","productName":"flour","volume":483840000,"volumeChange":0.11800000000000001,"amount":5244073,"amountChange":0.11199999999999999,"priceLevel":64.49,"sellers":13,"sellersChange":0,"divisions":103,"divisionsChange":13,"competition":1,"price":92.2,"priceChange":0.88,"quality":17.7,"qualityChange":0.19},{"productId":51,"product":"Мясо","productName":"meat","volume":569790000,"volumeChange":-0.013999999999999999,"amount":785722,"amountChange":-0.024,"priceLevel":72.76,"sellers":19,"sellersChange":1,"divisions":229,"divisionsChange":13,"competition":2,"price":728,"priceChange":9.18,"quality":15.86,"qualityChange":0.16},{"productId":441,"product":"Огурцы","productName":"cucumber","volume":326030000,"volumeChange":-0.006,"amount":2385662,"amountChange":-0.001,"priceLevel":60.7,"sellers":14,"sellersChange":0,"divisions":137,"divisionsChange":0,"competition":1,"price":136,"priceChange":-1.34,"quality":20.99,"qualityChange":-0.03},{"productId":101,"product":"Печенье","productName":"cookies","volume":405240000,"volumeChange":-0.08900000000000001,"amount":255034,"amountChange":-0.071,"priceLevel":100,"sellers":17,"sellersChange":1,"divisions":151,"divisionsChange":13,"competition":1,"price":1582,"priceChange":-37.01,"quality":17.73,"qualityChange":-0.24},{"productId":89,"product":"Пиво","productName":"beer","volume":518200000.00000006,"volumeChange":0.004,"amount":737938,"amountChange":0.002,"priceLevel":82.74,"sellers":18,"sellersChange":1,"divisions":186,"divisionsChange":17,"competition":2,"price":701,"priceChange":0.29,"quality":19.46,"qualityChange":0.06},{"productId":442,"product":"Помидоры","productName":"tomato","volume":352160000,"volumeChange":-0.02,"amount":1207398,"amountChange":-0.017,"priceLevel":67.9,"sellers":18,"sellersChange":0,"divisions":143,"divisionsChange":10,"competition":1,"price":291,"priceChange":-2.61,"quality":19.32,"qualityChange":-0.17},{"productId":94,"product":"Прохладительные напитки","productName":"gaswater","volume":514419999.99999994,"volumeChange":0.03,"amount":1953001,"amountChange":0.022000000000000002,"priceLevel":45.87,"sellers":17,"sellersChange":2,"divisions":200,"divisionsChange":21,"competition":2,"price":263,"priceChange":2.72,"quality":18.38,"qualityChange":0.29},{"productId":50,"product":"Растительное масло","productName":"fat","volume":484400000,"volumeChange":-0.043,"amount":1634048,"amountChange":-0.033,"priceLevel":51.99,"sellers":15,"sellersChange":1,"divisions":133,"divisionsChange":18,"competition":1,"price":293,"priceChange":-12.5,"quality":17.68,"qualityChange":-0.85},{"productId":56,"product":"Рыба","productName":"fish","volume":723800000,"volumeChange":0.002,"amount":253342,"amountChange":0.003,"priceLevel":56.15,"sellers":20,"sellersChange":2,"divisions":235,"divisionsChange":20,"competition":2,"price":2866,"priceChange":4.6,"quality":19.85,"qualityChange":0},{"productId":57,"product":"Сахар","productName":"sugar","volume":467700000,"volumeChange":0.064,"amount":2667452,"amountChange":0.062,"priceLevel":79.92,"sellers":16,"sellersChange":2,"divisions":115,"divisionsChange":18,"competition":1,"price":175,"priceChange":0.75,"quality":19.25,"qualityChange":0.2},{"productId":260,"product":"Свекла","productName":"beet","volume":593880000,"volumeChange":0.052000000000000005,"amount":7104024,"amountChange":0.033,"priceLevel":94.07,"sellers":13,"sellersChange":1,"divisions":150,"divisionsChange":11,"competition":1,"price":84.5,"priceChange":2.02,"quality":18.94,"qualityChange":0.02},{"productId":95,"product":"Сок","productName":"juice","volume":486400000,"volumeChange":-0.03,"amount":852114,"amountChange":-0.027999999999999997,"priceLevel":71.82,"sellers":22,"sellersChange":1,"divisions":209,"divisionsChange":9,"competition":2,"price":571,"priceChange":-0.85,"quality":19.17,"qualityChange":0.03},{"productId":83,"product":"Сыр","productName":"cheese","volume":428650000,"volumeChange":0.087,"amount":163257,"amountChange":0.106,"priceLevel":37.59,"sellers":15,"sellersChange":-1,"divisions":165,"divisionsChange":-1,"competition":1,"price":2630,"priceChange":-65.93,"quality":17.62,"qualityChange":-0.39},{"productId":102,"product":"Торт","productName":"cake","volume":446790000,"volumeChange":0.012,"amount":135690,"amountChange":0.01,"priceLevel":85.95,"sellers":20,"sellersChange":2,"divisions":180,"divisionsChange":15,"competition":2,"price":3295,"priceChange":7.73,"quality":18.09,"qualityChange":0.05},{"productId":312,"product":"Фрукты","productName":"fruits","volume":406480000,"volumeChange":-0.046,"amount":1675285,"amountChange":-0.03,"priceLevel":52,"sellers":15,"sellersChange":1,"divisions":147,"divisionsChange":7,"competition":2,"price":244,"priceChange":-4.06,"quality":17.99,"qualityChange":-0.21},{"productId":99,"product":"Хлеб","productName":"bread","volume":497700000,"volumeChange":-0.008,"amount":2767767,"amountChange":0.001,"priceLevel":68.09,"sellers":15,"sellersChange":1,"divisions":104,"divisionsChange":14,"competition":0,"price":180,"priceChange":-4.18,"quality":18.96,"qualityChange":-0.32},{"productId":103,"product":"Шоколад","productName":"chocolate","volume":614720000,"volumeChange":0.009000000000000001,"amount":1010009,"amountChange":0.023,"priceLevel":69.22,"sellers":21,"sellersChange":1,"divisions":181,"divisionsChange":17,"competition":1,"price":608,"priceChange":-8.36,"quality":18.16,"qualityChange":-0.25},{"productId":250,"product":"Яблоки","productName":"apples","volume":487300000,"volumeChange":-0.032,"amount":4875638,"amountChange":-0.04,"priceLevel":44.57,"sellers":17,"sellersChange":1,"divisions":147,"divisionsChange":6,"competition":1,"price":100,"priceChange":1.4,"quality":18.82,"qualityChange":-0.03},{"productId":72,"product":"Яйца","productName":"eggs","volume":706890000,"volumeChange":-0.035,"amount":2526298,"amountChange":-0.031,"priceLevel":63.18,"sellers":15,"sellersChange":0,"divisions":196,"divisionsChange":2,"competition":1,"price":280,"priceChange":-0.86,"quality":16.02,"qualityChange":-0.08}]},{"groupId":2,"group":"Товары для дома","groupName":"housegoods","turnover":9810000000,"turnoverChange":-0.023,"share":0.11380000000000001,"margin":1.57,"competition":1,"priceLevel":47.11,"products":[{"productId":375,"product":"Батарейка","productName":"battery","volume":390180000,"volumeChange":-0.015,"amount":621571,"amountChange":-0.013999999999999999,"priceLevel":30.1,"sellers":7,"sellersChange":1,"divisions":56,"divisionsChange":8,"competition":1,"price":628,"priceChange":-0.36,"quality":18.41,"qualityChange":0.03},{"productId":17,"product":"Бумага","productName":"paper","volume":283600000,"volumeChange":-0.047,"amount":344293,"amountChange":-0.057999999999999996,"priceLevel":45.94,"sellers":7,"sellersChange":0,"divisions":36,"divisionsChange":4,"competition":0,"price":837,"priceChange":16.71,"quality":18.64,"qualityChange":-0.16},{"productId":131,"product":"Диван","productName":"sofa","volume":400070000,"volumeChange":0.012,"amount":2652,"amountChange":0.023,"priceLevel":42.63,"sellers":8,"sellersChange":1,"divisions":74,"divisionsChange":7,"competition":1,"price":151383,"priceChange":409.61,"quality":17.52,"qualityChange":0.15},{"productId":150,"product":"Зонт","productName":"umbrella","volume":268820000,"volumeChange":-0.02,"amount":71378,"amountChange":-0.018000000000000002,"priceLevel":26.33,"sellers":6,"sellersChange":1,"divisions":48,"divisionsChange":1,"competition":1,"price":3804,"priceChange":5.32,"quality":18.63,"qualityChange":0.06},{"productId":108,"product":"Зубная паста","productName":"toothpaste","volume":693540000,"volumeChange":-0.01,"amount":2352885,"amountChange":-0.008,"priceLevel":88.31,"sellers":12,"sellersChange":2,"divisions":96,"divisionsChange":17,"competition":1,"price":299,"priceChange":-4.08,"quality":18.85,"qualityChange":-0.08},{"productId":452,"product":"Кастрюля","productName":"casserole","volume":254420000,"volumeChange":-0.024,"amount":19750,"amountChange":-0.023,"priceLevel":40.41,"sellers":6,"sellersChange":0,"divisions":32,"divisionsChange":0,"competition":1,"price":12882,"priceChange":-11.53,"quality":19.07,"qualityChange":0},{"productId":451,"product":"Комод","productName":"dresser","volume":666260000,"volumeChange":-0.071,"amount":18725,"amountChange":-0.07400000000000001,"priceLevel":38.35,"sellers":7,"sellersChange":-1,"divisions":89,"divisionsChange":-12,"competition":1,"price":35533,"priceChange":35.28,"quality":18.24,"qualityChange":0.06},{"productId":463,"product":"Кофемашина","productName":"coffeemachine","volume":179160000,"volumeChange":-0.07,"amount":1886,"amountChange":-0.076,"priceLevel":33.76,"sellers":6,"sellersChange":0,"divisions":45,"divisionsChange":0,"competition":1,"price":95212,"priceChange":117.03,"quality":20.66,"qualityChange":-0.06},{"productId":132,"product":"Кресло","productName":"chair","volume":443760000,"volumeChange":0.021,"amount":7537,"amountChange":0.026000000000000002,"priceLevel":49.66,"sellers":9,"sellersChange":1,"divisions":133,"divisionsChange":15,"competition":2,"price":58748,"priceChange":-614.22,"quality":18.15,"qualityChange":-0.31},{"productId":135,"product":"Кровать","productName":"bed","volume":434260000,"volumeChange":0.076,"amount":10306,"amountChange":0.096,"priceLevel":43.27,"sellers":9,"sellersChange":2,"divisions":134,"divisionsChange":32,"competition":2,"price":42115,"priceChange":-1016.05,"quality":18.39,"qualityChange":-0.46},{"productId":408,"product":"Кухонный гарнитур","productName":"kitchen","volume":258930000,"volumeChange":-0.153,"amount":1280,"amountChange":-0.153,"priceLevel":30.19,"sellers":10,"sellersChange":2,"divisions":114,"divisionsChange":18,"competition":2,"price":202708,"priceChange":1076.36,"quality":17.91,"qualityChange":0.15},{"productId":107,"product":"Моющее средство","productName":"detergent","volume":311660000,"volumeChange":-0.01,"amount":133346,"amountChange":-0.004,"priceLevel":63.83,"sellers":9,"sellersChange":0,"divisions":62,"divisionsChange":0,"competition":1,"price":2333,"priceChange":-19,"quality":18.43,"qualityChange":0},{"productId":105,"product":"Мыло","productName":"soap","volume":500090000,"volumeChange":-0.037000000000000005,"amount":553851,"amountChange":-0.034,"priceLevel":91.99,"sellers":11,"sellersChange":1,"divisions":80,"divisionsChange":1,"competition":1,"price":900,"priceChange":-4.45,"quality":19.65,"qualityChange":-0.01},{"productId":454,"product":"Полотенце","productName":"towel","volume":412560000,"volumeChange":0.048,"amount":101999,"amountChange":0.040999999999999995,"priceLevel":33.48,"sellers":8,"sellersChange":0,"divisions":58,"divisionsChange":0,"competition":1,"price":4131,"priceChange":36.51,"quality":19.72,"qualityChange":0.27},{"productId":319,"product":"Постельные принадлежности","productName":"beddress","volume":333480000,"volumeChange":-0.042,"amount":63523,"amountChange":-0.038,"priceLevel":49.05,"sellers":9,"sellersChange":0,"divisions":79,"divisionsChange":0,"competition":1,"price":5250,"priceChange":-4.77,"quality":19.25,"qualityChange":-0.04},{"productId":153,"product":"Посуда","productName":"dishes","volume":206310000,"volumeChange":-0.023,"amount":48261,"amountChange":-0.024,"priceLevel":22.01,"sellers":7,"sellersChange":0,"divisions":43,"divisionsChange":0,"competition":0,"price":4275,"priceChange":3.71,"quality":22.39,"qualityChange":0.02},{"productId":373,"product":"Пылесос","productName":"cleaner","volume":373300000,"volumeChange":-0.06,"amount":8012,"amountChange":-0.062,"priceLevel":27,"sellers":10,"sellersChange":1,"divisions":61,"divisionsChange":1,"competition":1,"price":46656,"priceChange":-48.49,"quality":18.66,"qualityChange":0.12},{"productId":158,"product":"Сковорода","productName":"pan","volume":204100000,"volumeChange":-0.053,"amount":40818,"amountChange":-0.06,"priceLevel":15.5,"sellers":6,"sellersChange":0,"divisions":42,"divisionsChange":0,"competition":0,"price":5006,"priceChange":46.21,"quality":19.11,"qualityChange":0.01},{"productId":106,"product":"Стиральный порошок","productName":"soappowder","volume":687300000,"volumeChange":-0.047,"amount":125392,"amountChange":-0.047,"priceLevel":68.61,"sellers":12,"sellersChange":0,"divisions":96,"divisionsChange":0,"competition":1,"price":5476,"priceChange":-21,"quality":18.96,"qualityChange":0.16},{"productId":134,"product":"Стол","productName":"table","volume":623260000,"volumeChange":-0.06,"amount":18999,"amountChange":-0.059000000000000004,"priceLevel":51.4,"sellers":9,"sellersChange":0,"divisions":134,"divisionsChange":0,"competition":2,"price":32781,"priceChange":-9.95,"quality":16.76,"qualityChange":0.07},{"productId":445,"product":"Стремянка","productName":"ladder","volume":258240000,"volumeChange":-0.03,"amount":13469,"amountChange":-0.032,"priceLevel":33.66,"sellers":10,"sellersChange":0,"divisions":50,"divisionsChange":0,"competition":1,"price":19183,"priceChange":45.89,"quality":18.89,"qualityChange":-0.01},{"productId":420,"product":"Стул","productName":"stool","volume":473800000,"volumeChange":0.08,"amount":59754,"amountChange":0.076,"priceLevel":21.6,"sellers":9,"sellersChange":-1,"divisions":116,"divisionsChange":-4,"competition":2,"price":7930,"priceChange":9.63,"quality":17.79,"qualityChange":0.01},{"productId":113,"product":"Утюг","productName":"iron","volume":443940000,"volumeChange":-0.037000000000000005,"amount":52188,"amountChange":-0.042,"priceLevel":32.65,"sellers":10,"sellersChange":0,"divisions":60,"divisionsChange":0,"competition":0,"price":8506,"priceChange":37.94,"quality":18.33,"qualityChange":0.06},{"productId":320,"product":"Чайник","productName":"teapot","volume":74190000,"volumeChange":-0.022000000000000002,"amount":10401,"amountChange":-0.006,"priceLevel":69.82,"sellers":7,"sellersChange":0,"divisions":27,"divisionsChange":0,"competition":1,"price":7082,"priceChange":-144.77,"quality":20.16,"qualityChange":0},{"productId":133,"product":"Шкаф","productName":"wardrobe","volume":637110000,"volumeChange":-0.006999999999999999,"amount":4150,"amountChange":-0.009000000000000001,"priceLevel":46.96,"sellers":11,"sellersChange":1,"divisions":128,"divisionsChange":1,"competition":1,"price":153528,"priceChange":23.66,"quality":17.73,"qualityChange":0}]},{"groupId":3,"group":"Одежда","groupName":"clothes","turnover":14910000000,"turnoverChange":-0.026000000000000002,"share":0.1729,"margin":1.62,"competition":2,"priceLevel":48.55,"products":[{"productId":207,"product":"Блузка","productName":"blouse","volume":721160000,"volumeChange":-0.009000000000000001,"amount":144715,"amountChange":-0.02,"priceLevel":47.13,"sellers":12,"sellersChange":0,"divisions":152,"divisionsChange":0,"competition":2,"price":4998,"priceChange":57.43,"quality":17.19,"qualityChange":-0.03},{"productId":137,"product":"Ботинки","productName":"manshoes","volume":701220000,"volumeChange":-0.031,"amount":48296,"amountChange":-0.027999999999999997,"priceLevel":53.65,"sellers":12,"sellersChange":0,"divisions":110,"divisionsChange":0,"competition":1,"price":14429,"priceChange":-136.01,"quality":16.31,"qualityChange":-0.04},{"productId":462,"product":"Галстук","productName":"tie","volume":574510000,"volumeChange":-0.033,"amount":105196,"amountChange":-0.028999999999999998,"priceLevel":55.29,"sellers":14,"sellersChange":0,"divisions":135,"divisionsChange":0,"competition":2,"price":5448,"priceChange":-33.98,"quality":17.22,"qualityChange":0.03},{"productId":396,"product":"Джинсы","productName":"jeans","volume":530450000.00000006,"volumeChange":0.008,"amount":37142,"amountChange":0.013999999999999999,"priceLevel":68.35,"sellers":14,"sellersChange":0,"divisions":119,"divisionsChange":1,"competition":2,"price":14241,"priceChange":-122.52,"quality":16.78,"qualityChange":0.02},{"productId":460,"product":"Дубленка","productName":"sheepskin","volume":485360000,"volumeChange":0.011000000000000001,"amount":8216,"amountChange":0.015,"priceLevel":43.5,"sellers":14,"sellersChange":0,"divisions":180,"divisionsChange":0,"competition":2,"price":58932,"priceChange":-369.17,"quality":16.59,"qualityChange":0.05},{"productId":204,"product":"Костюм","productName":"suit","volume":337450000,"volumeChange":-0.037000000000000005,"amount":15333,"amountChange":-0.034,"priceLevel":63.27,"sellers":13,"sellersChange":0,"divisions":120,"divisionsChange":0,"competition":1,"price":21972,"priceChange":-116.28,"quality":16.94,"qualityChange":0.02},{"productId":203,"product":"Куртка","productName":"jacket","volume":588300000,"volumeChange":0.001,"amount":34457,"amountChange":0.006,"priceLevel":43.13,"sellers":13,"sellersChange":0,"divisions":144,"divisionsChange":1,"competition":2,"price":17033,"priceChange":-111.83,"quality":16.43,"qualityChange":0.02},{"productId":326,"product":"Носки","productName":"socks","volume":608450000,"volumeChange":-0.027999999999999997,"amount":3325504,"amountChange":-0.025,"priceLevel":25.67,"sellers":16,"sellersChange":0,"divisions":140,"divisionsChange":0,"competition":2,"price":183,"priceChange":0.42,"quality":17.56,"qualityChange":-0.01},{"productId":206,"product":"Пальто","productName":"mancoat","volume":510530000,"volumeChange":-0.035,"amount":17562,"amountChange":-0.033,"priceLevel":57.74,"sellers":16,"sellersChange":0,"divisions":160,"divisionsChange":0,"competition":2,"price":29049,"priceChange":-82.51,"quality":17.37,"qualityChange":0},{"productId":149,"product":"Перчатки","productName":"gloves","volume":507430000,"volumeChange":-0.032,"amount":268003,"amountChange":-0.033,"priceLevel":29.12,"sellers":14,"sellersChange":0,"divisions":168,"divisionsChange":1,"competition":2,"price":1893,"priceChange":-0.29,"quality":16.84,"qualityChange":0.02},{"productId":208,"product":"Платье","productName":"dress","volume":642410000,"volumeChange":0.036000000000000004,"amount":59913,"amountChange":0.033,"priceLevel":26.26,"sellers":13,"sellersChange":1,"divisions":153,"divisionsChange":11,"competition":2,"price":10729,"priceChange":4.04,"quality":16.89,"qualityChange":-0.01},{"productId":435,"product":"Пуховик","productName":"downjacket","volume":459830000,"volumeChange":-0.038,"amount":15365,"amountChange":-0.034,"priceLevel":41.49,"sellers":16,"sellersChange":0,"divisions":158,"divisionsChange":0,"competition":2,"price":29873,"priceChange":-176.01,"quality":17.2,"qualityChange":0},{"productId":148,"product":"Ремень","productName":"belt","volume":778190000,"volumeChange":-0.022000000000000002,"amount":169835,"amountChange":-0.01,"priceLevel":58.55,"sellers":13,"sellersChange":0,"divisions":122,"divisionsChange":0,"competition":2,"price":4559,"priceChange":-65.24,"quality":16.37,"qualityChange":0.03},{"productId":205,"product":"Рубашка","productName":"shirt","volume":575920000,"volumeChange":0.009000000000000001,"amount":112508,"amountChange":0.038,"priceLevel":49.72,"sellers":12,"sellersChange":0,"divisions":106,"divisionsChange":0,"competition":1,"price":5061,"priceChange":-180.22,"quality":17.56,"qualityChange":0},{"productId":458,"product":"Сапоги","productName":"boots","volume":546550000,"volumeChange":-0.024,"amount":18095,"amountChange":-0.023,"priceLevel":23.59,"sellers":14,"sellersChange":0,"divisions":134,"divisionsChange":0,"competition":1,"price":30176,"priceChange":-30.06,"quality":16.32,"qualityChange":0.01},{"productId":461,"product":"Свитер","productName":"sweater","volume":590090000,"volumeChange":-0.037000000000000005,"amount":44323,"amountChange":-0.040999999999999995,"priceLevel":43.4,"sellers":13,"sellersChange":-1,"divisions":152,"divisionsChange":-1,"competition":2,"price":13330,"priceChange":57.29,"quality":16.89,"qualityChange":0},{"productId":459,"product":"Сланцы","productName":"slates","volume":768320000,"volumeChange":-0.018000000000000002,"amount":324167,"amountChange":-0.011000000000000001,"priceLevel":84.65,"sellers":14,"sellersChange":0,"divisions":111,"divisionsChange":0,"competition":1,"price":2367,"priceChange":-20.62,"quality":15.22,"qualityChange":0.05},{"productId":436,"product":"Толстовка","productName":"sweatshirt","volume":525950000.00000006,"volumeChange":-0.025,"amount":43210,"amountChange":-0.021,"priceLevel":52.56,"sellers":13,"sellersChange":0,"divisions":121,"divisionsChange":0,"competition":2,"price":12144,"priceChange":-70.34,"quality":16.71,"qualityChange":0.01},{"productId":138,"product":"Туфли","productName":"womanshoes","volume":609920000,"volumeChange":-0.054000000000000006,"amount":51743,"amountChange":-0.049,"priceLevel":35.4,"sellers":16,"sellersChange":0,"divisions":140,"divisionsChange":0,"competition":1,"price":11742,"priceChange":-107.51,"quality":16.12,"qualityChange":-0.08},{"productId":395,"product":"Футболка","productName":"tshirt","volume":503840000,"volumeChange":0.001,"amount":156518,"amountChange":0,"priceLevel":42.15,"sellers":12,"sellersChange":0,"divisions":152,"divisionsChange":0,"competition":3,"price":3228,"priceChange":12.3,"quality":17.54,"qualityChange":-0.09},{"productId":397,"product":"Шапка","productName":"cap","volume":731850000,"volumeChange":-0.02,"amount":170449,"amountChange":-0.023,"priceLevel":62.06,"sellers":16,"sellersChange":0,"divisions":140,"divisionsChange":1,"competition":1,"price":4300,"priceChange":20.93,"quality":17.38,"qualityChange":0.01},{"productId":439,"product":"Шарф","productName":"scarf","volume":879380000,"volumeChange":-0.11199999999999999,"amount":411080,"amountChange":-0.107,"priceLevel":44.7,"sellers":14,"sellersChange":-1,"divisions":151,"divisionsChange":-30,"competition":1,"price":2128,"priceChange":-25.76,"quality":17.28,"qualityChange":-0.23},{"productId":434,"product":"Шорты","productName":"shorts","volume":532260000,"volumeChange":-0.008,"amount":100627,"amountChange":0,"priceLevel":56.96,"sellers":14,"sellersChange":0,"divisions":116,"divisionsChange":0,"competition":1,"price":5271,"priceChange":-53.46,"quality":17.24,"qualityChange":0.02},{"productId":210,"product":"Шуба","productName":"furcoat","volume":437990000,"volumeChange":-0.054000000000000006,"amount":4522,"amountChange":-0.05,"priceLevel":40.49,"sellers":14,"sellersChange":0,"divisions":177,"divisionsChange":0,"competition":2,"price":96722,"priceChange":-521.9,"quality":16.65,"qualityChange":0.02},{"productId":433,"product":"Юбка","productName":"skirt","volume":762790000,"volumeChange":-0.05,"amount":76940,"amountChange":-0.046,"priceLevel":51.85,"sellers":13,"sellersChange":0,"divisions":153,"divisionsChange":0,"competition":2,"price":9915,"priceChange":-5.1,"quality":17.36,"qualityChange":-0.01}]},{"groupId":12,"group":"Фармацевтика","groupName":"pharma","turnover":6450000000,"turnoverChange":-0.027000000000000003,"share":0.0747,"margin":1.56,"competition":2,"priceLevel":57.93,"products":[{"productId":344,"product":"Антибиотики","productName":"antibiotics","volume":554100000,"volumeChange":0.095,"amount":95645,"amountChange":0.08199999999999999,"priceLevel":73.36,"sellers":11,"sellersChange":1,"divisions":206,"divisionsChange":19,"competition":3,"price":5940,"priceChange":107.12,"quality":17.88,"qualityChange":-0.47},{"productId":416,"product":"Антисептик","productName":"antiseptic","volume":497370000,"volumeChange":-0.044000000000000004,"amount":478646,"amountChange":-0.055999999999999994,"priceLevel":43.68,"sellers":11,"sellersChange":0,"divisions":206,"divisionsChange":0,"competition":3,"price":1062,"priceChange":35.46,"quality":17.56,"qualityChange":-0.02},{"productId":334,"product":"БАД","productName":"supplements","volume":295150000,"volumeChange":-0.039,"amount":52570,"amountChange":-0.039,"priceLevel":27.93,"sellers":9,"sellersChange":1,"divisions":162,"divisionsChange":6,"competition":2,"price":5724,"priceChange":111.75,"quality":16.93,"qualityChange":-0.25},{"productId":343,"product":"Вакцина","productName":"vaccine","volume":452990000,"volumeChange":0.015,"amount":91403,"amountChange":-0.02,"priceLevel":51.29,"sellers":10,"sellersChange":-1,"divisions":174,"divisionsChange":-7,"competition":2,"price":5084,"priceChange":271.86,"quality":18.64,"qualityChange":0.24},{"productId":333,"product":"Витамины","productName":"vitamins","volume":464730000,"volumeChange":-0.065,"amount":249384,"amountChange":-0.079,"priceLevel":49.67,"sellers":12,"sellersChange":0,"divisions":189,"divisionsChange":0,"competition":2,"price":1898,"priceChange":63.23,"quality":17.73,"qualityChange":-0.04},{"productId":337,"product":"Контрацептивы","productName":"contraceptives","volume":325390000,"volumeChange":-0.049,"amount":457380,"amountChange":-0.07200000000000001,"priceLevel":18.92,"sellers":13,"sellersChange":0,"divisions":149,"divisionsChange":0,"competition":2,"price":732,"priceChange":36.87,"quality":16.01,"qualityChange":0.1},{"productId":384,"product":"Лечебный крем","productName":"healingcream","volume":319840000,"volumeChange":-0.057,"amount":54438,"amountChange":-0.075,"priceLevel":40.91,"sellers":10,"sellersChange":0,"divisions":135,"divisionsChange":0,"competition":2,"price":6027,"priceChange":234.18,"quality":16.61,"qualityChange":-0.04},{"productId":455,"product":"Линзы","productName":"lenses","volume":306220000,"volumeChange":0.06,"amount":184403,"amountChange":0.01,"priceLevel":39.01,"sellers":9,"sellersChange":0,"divisions":111,"divisionsChange":0,"competition":1,"price":1716,"priceChange":119.37,"quality":16.03,"qualityChange":-0.06},{"productId":339,"product":"Мед техника","productName":"medtechnic","volume":293020000,"volumeChange":0.006,"amount":4407,"amountChange":-0.016,"priceLevel":56.57,"sellers":11,"sellersChange":-2,"divisions":142,"divisionsChange":-11,"competition":2,"price":68153,"priceChange":3113.43,"quality":20.66,"qualityChange":0.03},{"productId":336,"product":"Настойка","productName":"tincture","volume":500690000,"volumeChange":-0.064,"amount":115488,"amountChange":-0.079,"priceLevel":91.2,"sellers":13,"sellersChange":0,"divisions":211,"divisionsChange":0,"competition":3,"price":4429,"priceChange":164.61,"quality":16.66,"qualityChange":-0.04},{"productId":340,"product":"Ортопедические изделия","productName":"orthopedic","volume":223840000,"volumeChange":-0.08900000000000001,"amount":30236,"amountChange":-0.11,"priceLevel":35.27,"sellers":12,"sellersChange":0,"divisions":146,"divisionsChange":0,"competition":2,"price":7614,"priceChange":395.23,"quality":15.54,"qualityChange":0.09},{"productId":338,"product":"Перевязочные средства","productName":"bandage","volume":694670000,"volumeChange":-0.008,"amount":751068,"amountChange":-0.009000000000000001,"priceLevel":98.28,"sellers":13,"sellersChange":0,"divisions":216,"divisionsChange":0,"competition":3,"price":927,"priceChange":1.58,"quality":16.28,"qualityChange":-0.05},{"productId":342,"product":"Противопростудные","productName":"cough","volume":504560000,"volumeChange":-0.06,"amount":109746,"amountChange":-0.067,"priceLevel":43.09,"sellers":13,"sellersChange":0,"divisions":218,"divisionsChange":0,"competition":3,"price":4667,"priceChange":113.17,"quality":17.66,"qualityChange":-0.06},{"productId":341,"product":"Рецептурные препараты","productName":"prescription","volume":552570000,"volumeChange":-0.038,"amount":262243,"amountChange":-0.05,"priceLevel":65.75,"sellers":11,"sellersChange":-2,"divisions":211,"divisionsChange":-7,"competition":3,"price":2163,"priceChange":83.53,"quality":17.27,"qualityChange":0.05},{"productId":418,"product":"Травяной сбор","productName":"herbal","volume":461440000,"volumeChange":-0.067,"amount":362905,"amountChange":-0.083,"priceLevel":61.95,"sellers":12,"sellersChange":2,"divisions":213,"divisionsChange":23,"competition":3,"price":1300,"priceChange":39.93,"quality":17.49,"qualityChange":0.11}]},{"groupId":4,"group":"Электроника","groupName":"electronics","turnover":12110000000,"turnoverChange":0.019,"share":0.1405,"margin":1.35,"competition":1,"priceLevel":48.5,"products":[{"productId":117,"product":"Аудиотехника","productName":"audio","volume":441960000,"volumeChange":0.872,"amount":14078,"amountChange":0.87,"priceLevel":13.31,"sellers":14,"sellersChange":4,"divisions":99,"divisionsChange":27,"competition":1,"price":31550,"priceChange":240.17,"quality":20.71,"qualityChange":-0.48},{"productId":409,"product":"Варочная панель","productName":"hob","volume":999340000,"volumeChange":0.042,"amount":29818,"amountChange":0.044000000000000004,"priceLevel":48.38,"sellers":14,"sellersChange":4,"divisions":157,"divisionsChange":16,"competition":2,"price":33778,"priceChange":306.36,"quality":19.4,"qualityChange":0.26},{"productId":410,"product":"Вытяжка","productName":"hood","volume":696200000,"volumeChange":-0.129,"amount":27597,"amountChange":-0.133,"priceLevel":67.13,"sellers":13,"sellersChange":1,"divisions":149,"divisionsChange":4,"competition":1,"price":25288,"priceChange":106.49,"quality":19.61,"qualityChange":0.23},{"productId":318,"product":"Игровая приставка","productName":"xbox","volume":261149999.99999997,"volumeChange":0.5379999999999999,"amount":5315,"amountChange":0.617,"priceLevel":77.71,"sellers":8,"sellersChange":2,"divisions":91,"divisionsChange":11,"competition":1,"price":49334,"priceChange":-134.51,"quality":17.8,"qualityChange":0.93},{"productId":381,"product":"Кухонный комбайн","productName":"foodprocessor","volume":642050000,"volumeChange":0.128,"amount":10123,"amountChange":0.126,"priceLevel":30.11,"sellers":14,"sellersChange":3,"divisions":155,"divisionsChange":35,"competition":1,"price":63532,"priceChange":60.34,"quality":19.14,"qualityChange":-0.33},{"productId":316,"product":"Микроволновка","productName":"microwave","volume":787340000,"volumeChange":-0.063,"amount":9822,"amountChange":-0.063,"priceLevel":53.78,"sellers":14,"sellersChange":0,"divisions":156,"divisionsChange":0,"competition":1,"price":80154,"priceChange":-31.11,"quality":19.21,"qualityChange":-0.01},{"productId":125,"product":"Настольный компьютер","productName":"computer","volume":531150000,"volumeChange":0.022000000000000002,"amount":4004,"amountChange":0.05,"priceLevel":59.1,"sellers":9,"sellersChange":-2,"divisions":125,"divisionsChange":-2,"competition":1,"price":132564,"priceChange":-256.22,"quality":18.86,"qualityChange":-0.05},{"productId":371,"product":"Наушники","productName":"headphones","volume":823920000,"volumeChange":0.43,"amount":71256,"amountChange":0.442,"priceLevel":56.2,"sellers":10,"sellersChange":0,"divisions":130,"divisionsChange":0,"competition":1,"price":11569,"priceChange":11.82,"quality":19.22,"qualityChange":0.12},{"productId":126,"product":"Ноутбук","productName":"notebook","volume":340090000,"volumeChange":-0.012,"amount":2332,"amountChange":-0.006,"priceLevel":30.7,"sellers":10,"sellersChange":1,"divisions":125,"divisionsChange":2,"competition":1,"price":143121,"priceChange":-104.7,"quality":19.3,"qualityChange":-0.29},{"productId":317,"product":"Планшет","productName":"tablet","volume":412730000,"volumeChange":-0.07200000000000001,"amount":10022,"amountChange":-0.062,"priceLevel":48.55,"sellers":8,"sellersChange":-2,"divisions":110,"divisionsChange":-16,"competition":1,"price":41251,"priceChange":107.32,"quality":18.3,"qualityChange":-0.21},{"productId":112,"product":"Посудомоечная машина","productName":"dishwasher","volume":568040000,"volumeChange":0.086,"amount":4043,"amountChange":0.092,"priceLevel":34.41,"sellers":13,"sellersChange":1,"divisions":152,"divisionsChange":21,"competition":2,"price":139997,"priceChange":-1261.28,"quality":19.9,"qualityChange":0.2},{"productId":128,"product":"Принтер","productName":"printer","volume":545410000,"volumeChange":-0.036000000000000004,"amount":6135,"amountChange":-0.03,"priceLevel":48.59,"sellers":10,"sellersChange":1,"divisions":129,"divisionsChange":1,"competition":1,"price":88821,"priceChange":-362.61,"quality":18.91,"qualityChange":0.69},{"productId":372,"product":"Смарт часы","productName":"smartwatch","volume":456410000,"volumeChange":-0.1,"amount":23677,"amountChange":-0.1,"priceLevel":77.94,"sellers":9,"sellersChange":0,"divisions":127,"divisionsChange":0,"competition":1,"price":19284,"priceChange":2.04,"quality":18.13,"qualityChange":-0.19},{"productId":129,"product":"Смартфон","productName":"smartphone","volume":662300000,"volumeChange":0.127,"amount":15612,"amountChange":0.136,"priceLevel":63.05,"sellers":9,"sellersChange":-1,"divisions":123,"divisionsChange":-2,"competition":1,"price":42338,"priceChange":-199.67,"quality":18.02,"qualityChange":0.22},{"productId":456,"product":"Спутниковое оборудование","productName":"satellite","volume":697060000,"volumeChange":-0.061,"amount":18254,"amountChange":-0.061,"priceLevel":50.56,"sellers":12,"sellersChange":0,"divisions":130,"divisionsChange":0,"competition":1,"price":38184,"priceChange":-5.11,"quality":19.86,"qualityChange":0.02},{"productId":111,"product":"Стиральная машина","productName":"washer","volume":490080000,"volumeChange":-0.043,"amount":4578,"amountChange":-0.039,"priceLevel":51.89,"sellers":11,"sellersChange":4,"divisions":145,"divisionsChange":37,"competition":1,"price":107219,"priceChange":-1222.92,"quality":18.26,"qualityChange":-0.5},{"productId":115,"product":"Телевизор","productName":"tv","volume":734630000,"volumeChange":-0.267,"amount":3399,"amountChange":-0.248,"priceLevel":35.5,"sellers":10,"sellersChange":0,"divisions":142,"divisionsChange":0,"competition":1,"price":216009,"priceChange":-23.67,"quality":18.69,"qualityChange":0.16},{"productId":457,"product":"Умная колонка","productName":"speaker","volume":567890000,"volumeChange":0.273,"amount":24788,"amountChange":0.261,"priceLevel":41.64,"sellers":11,"sellersChange":2,"divisions":166,"divisionsChange":20,"competition":1,"price":22939,"priceChange":229.76,"quality":18.74,"qualityChange":0.15},{"productId":151,"product":"Фотоаппарат","productName":"photo","volume":659970000,"volumeChange":-0.051,"amount":9549,"amountChange":-0.052000000000000005,"priceLevel":39.6,"sellers":14,"sellersChange":2,"divisions":118,"divisionsChange":5,"competition":1,"price":69124,"priceChange":68.03,"quality":19.7,"qualityChange":0},{"productId":110,"product":"Холодильник","productName":"refrigirator","volume":797210000,"volumeChange":-0.061,"amount":5045,"amountChange":-0.061,"priceLevel":45.94,"sellers":16,"sellersChange":0,"divisions":167,"divisionsChange":0,"competition":2,"price":158056,"priceChange":23.63,"quality":18.23,"qualityChange":-0.03}]},{"groupId":15,"group":"Услуги","groupName":"service","turnover":2000000000,"turnoverChange":-0.07200000000000001,"share":0.0232,"margin":0,"competition":2,"priceLevel":89.34,"products":[{"productId":466,"product":"Женская стрижка","productName":"womenhaircut","volume":276480000,"volumeChange":-0.027999999999999997,"amount":47032,"amountChange":-0.027999999999999997,"priceLevel":45.89,"sellers":6,"sellersChange":0,"divisions":43,"divisionsChange":0,"competition":1,"price":5878,"priceChange":4.27,"quality":12.82,"qualityChange":0},{"productId":467,"product":"Маникюр","productName":"manicure","volume":726900000,"volumeChange":-0.053,"amount":134033,"amountChange":-0.055,"priceLevel":99.26,"sellers":7,"sellersChange":0,"divisions":64,"divisionsChange":0,"competition":2,"price":5423,"priceChange":8.38,"quality":12.88,"qualityChange":0},{"productId":465,"product":"Мужская стрижка","productName":"menhaircut","volume":996480000,"volumeChange":-0.096,"amount":267619,"amountChange":-0.09699999999999999,"priceLevel":94.17,"sellers":7,"sellersChange":0,"divisions":72,"divisionsChange":0,"competition":2,"price":3724,"priceChange":2.38,"quality":12.92,"qualityChange":0}]},{"groupId":7,"group":"Стройматериалы","groupName":"constructive","turnover":5550000000,"turnoverChange":-0.047,"share":0.0644,"margin":1.63,"competition":2,"priceLevel":43.41,"products":[{"productId":348,"product":"Герметик","productName":"glue","volume":412720000,"volumeChange":-0.044000000000000004,"amount":599452,"amountChange":-0.031,"priceLevel":63.04,"sellers":13,"sellersChange":0,"divisions":151,"divisionsChange":0,"competition":2,"price":686,"priceChange":-13.35,"quality":17.84,"qualityChange":-0.3},{"productId":323,"product":"Дверь","productName":"door","volume":295420000,"volumeChange":-0.068,"amount":12986,"amountChange":-0.07,"priceLevel":33.92,"sellers":9,"sellersChange":0,"divisions":111,"divisionsChange":0,"competition":2,"price":22733,"priceChange":30.13,"quality":17.69,"qualityChange":0.08},{"productId":449,"product":"Зеркало","productName":"mirror","volume":214880000,"volumeChange":-0.049,"amount":14857,"amountChange":-0.049,"priceLevel":25.01,"sellers":6,"sellersChange":0,"divisions":59,"divisionsChange":0,"competition":1,"price":14442,"priceChange":2.85,"quality":19.42,"qualityChange":0.03},{"productId":244,"product":"Инструменты","productName":"tools","volume":237840000,"volumeChange":-0.02,"amount":4711,"amountChange":-0.022000000000000002,"priceLevel":7.89,"sellers":9,"sellersChange":0,"divisions":69,"divisionsChange":0,"competition":1,"price":50349,"priceChange":-9.67,"quality":19.4,"qualityChange":0.25},{"productId":324,"product":"Керамическая плитка","productName":"tile","volume":217690000,"volumeChange":-0.066,"amount":12100,"amountChange":-0.064,"priceLevel":39.67,"sellers":6,"sellersChange":0,"divisions":59,"divisionsChange":0,"competition":1,"price":17970,"priceChange":-107.9,"quality":19.62,"qualityChange":0.18},{"productId":446,"product":"Ковер","productName":"carpet","volume":153680000,"volumeChange":-0.057,"amount":5669,"amountChange":-0.059000000000000004,"priceLevel":30.23,"sellers":6,"sellersChange":0,"divisions":55,"divisionsChange":0,"competition":1,"price":27122,"priceChange":67.34,"quality":18.33,"qualityChange":0.03},{"productId":374,"product":"Кондиционер","productName":"conditioning","volume":251920000,"volumeChange":-0.039,"amount":1578,"amountChange":-0.04,"priceLevel":35.7,"sellers":10,"sellersChange":0,"divisions":97,"divisionsChange":0,"competition":2,"price":159601,"priceChange":29.69,"quality":19.79,"qualityChange":0.02},{"productId":32,"product":"Краска","productName":"paint","volume":305900000,"volumeChange":-0.045,"amount":14381,"amountChange":-0.04,"priceLevel":17.03,"sellers":9,"sellersChange":-1,"divisions":94,"divisionsChange":-3,"competition":2,"price":21247,"priceChange":-47.85,"quality":18.18,"qualityChange":-0.04},{"productId":419,"product":"Крепеж","productName":"fasteners","volume":346650000,"volumeChange":-0.062,"amount":49569,"amountChange":-0.061,"priceLevel":60.51,"sellers":9,"sellersChange":0,"divisions":104,"divisionsChange":0,"competition":2,"price":6993,"priceChange":5.5,"quality":17.7,"qualityChange":-0.06},{"productId":240,"product":"Напольные покрытия","productName":"floor","volume":266170000.00000003,"volumeChange":-0.057999999999999996,"amount":39883,"amountChange":-0.059000000000000004,"priceLevel":43.4,"sellers":9,"sellersChange":0,"divisions":112,"divisionsChange":0,"competition":2,"price":6671,"priceChange":8.21,"quality":18.12,"qualityChange":0},{"productId":407,"product":"Обогреватель","productName":"heater","volume":216240000,"volumeChange":-0.023,"amount":2860,"amountChange":-0.023,"priceLevel":28.25,"sellers":10,"sellersChange":0,"divisions":108,"divisionsChange":0,"competition":3,"price":75595,"priceChange":17.74,"quality":18.06,"qualityChange":-0.01},{"productId":239,"product":"Обои","productName":"wallpaper","volume":295160000,"volumeChange":-0.046,"amount":17120,"amountChange":-0.042,"priceLevel":96.42,"sellers":9,"sellersChange":0,"divisions":101,"divisionsChange":0,"competition":2,"price":17211,"priceChange":-57.68,"quality":18.28,"qualityChange":0.08},{"productId":249,"product":"Окна","productName":"window","volume":273900000,"volumeChange":-0.064,"amount":2859,"amountChange":-0.065,"priceLevel":54.85,"sellers":9,"sellersChange":0,"divisions":114,"divisionsChange":0,"competition":2,"price":95810,"priceChange":76.79,"quality":19.96,"qualityChange":-0.05},{"productId":370,"product":"Провода","productName":"wires","volume":380410000,"volumeChange":-0.047,"amount":38198,"amountChange":-0.048,"priceLevel":34.48,"sellers":12,"sellersChange":0,"divisions":147,"divisionsChange":0,"competition":2,"price":9958,"priceChange":0.67,"quality":18.29,"qualityChange":0.04},{"productId":242,"product":"Сантехника","productName":"sanitary","volume":223310000,"volumeChange":-0.049,"amount":11751,"amountChange":-0.049,"priceLevel":27.22,"sellers":6,"sellersChange":0,"divisions":59,"divisionsChange":0,"competition":1,"price":18999,"priceChange":-2.28,"quality":18.75,"qualityChange":0.02},{"productId":241,"product":"Светильник","productName":"lamp","volume":282650000,"volumeChange":-0.044000000000000004,"amount":15116,"amountChange":-0.04,"priceLevel":42.31,"sellers":9,"sellersChange":0,"divisions":76,"divisionsChange":0,"competition":2,"price":18673,"priceChange":-69.85,"quality":19.5,"qualityChange":-0.07},{"productId":411,"product":"Трубы","productName":"pipes","volume":304530000,"volumeChange":-0.057999999999999996,"amount":2202,"amountChange":-0.059000000000000004,"priceLevel":57.33,"sellers":9,"sellersChange":0,"divisions":111,"divisionsChange":0,"competition":2,"price":138261,"priceChange":90.11,"quality":18.21,"qualityChange":0.01},{"productId":447,"product":"Фурнитура","productName":"fittings","volume":350960000,"volumeChange":-0.06,"amount":57543,"amountChange":-0.06,"priceLevel":30.47,"sellers":13,"sellersChange":0,"divisions":149,"divisionsChange":0,"competition":3,"price":6103,"priceChange":-0.71,"quality":18.49,"qualityChange":-0.08},{"productId":412,"product":"Шторы","productName":"curtains","volume":188730000,"volumeChange":0.073,"amount":2187,"amountChange":0.054000000000000006,"priceLevel":22.91,"sellers":10,"sellersChange":0,"divisions":95,"divisionsChange":0,"competition":2,"price":86038,"priceChange":-385.66,"quality":18.25,"qualityChange":0.09},{"productId":448,"product":"Штукатурка","productName":"plaster","volume":334460000,"volumeChange":-0.057,"amount":42314,"amountChange":-0.054000000000000006,"priceLevel":73.44,"sellers":11,"sellersChange":0,"divisions":116,"divisionsChange":0,"competition":2,"price":7889,"priceChange":-48.73,"quality":11.16,"qualityChange":0}]},{"groupId":13,"group":"Спорттовары","groupName":"sport","turnover":5920000000,"turnoverChange":-0.016,"share":0.06860000000000001,"margin":1.54,"competition":1,"priceLevel":50.51,"products":[{"productId":120,"product":"Велосипед","productName":"bicycle","volume":211640000,"volumeChange":-0.052000000000000005,"amount":2663,"amountChange":-0.052000000000000005,"priceLevel":60.36,"sellers":5,"sellersChange":0,"divisions":53,"divisionsChange":0,"competition":1,"price":79232,"priceChange":-135.81,"quality":17.4,"qualityChange":-0.03},{"productId":350,"product":"Гантели","productName":"dumbbells","volume":359230000,"volumeChange":-0.057,"amount":75405,"amountChange":-0.055999999999999994,"priceLevel":70.59,"sellers":6,"sellersChange":0,"divisions":59,"divisionsChange":0,"competition":1,"price":4701,"priceChange":-4.1,"quality":16.87,"qualityChange":-0.01},{"productId":414,"product":"Коврик","productName":"rug","volume":261750000,"volumeChange":-0.039,"amount":92997,"amountChange":-0.039,"priceLevel":36.61,"sellers":5,"sellersChange":0,"divisions":53,"divisionsChange":0,"competition":1,"price":2811,"priceChange":-0.4,"quality":17.05,"qualityChange":0.01},{"productId":351,"product":"Компрессионная одежда","productName":"compression","volume":211340000,"volumeChange":-0.059000000000000004,"amount":12636,"amountChange":-0.059000000000000004,"priceLevel":56.89,"sellers":5,"sellersChange":0,"divisions":53,"divisionsChange":0,"competition":1,"price":16700,"priceChange":-0.61,"quality":18.35,"qualityChange":-0.02},{"productId":361,"product":"Коньки","productName":"skates","volume":300370000,"volumeChange":-0.045,"amount":18304,"amountChange":-0.047,"priceLevel":61.2,"sellers":8,"sellersChange":0,"divisions":82,"divisionsChange":0,"competition":2,"price":16361,"priceChange":19.67,"quality":17.61,"qualityChange":0},{"productId":140,"product":"Кросcовки","productName":"sportshoes","volume":199460000,"volumeChange":-0.07,"amount":27812,"amountChange":-0.069,"priceLevel":11.01,"sellers":5,"sellersChange":0,"divisions":53,"divisionsChange":0,"competition":1,"price":7158,"priceChange":-10.51,"quality":18.22,"qualityChange":-0.03},{"productId":362,"product":"Лыжи","productName":"skiing","volume":256860000,"volumeChange":0.036000000000000004,"amount":7909,"amountChange":0.033,"priceLevel":57.51,"sellers":6,"sellersChange":0,"divisions":71,"divisionsChange":0,"competition":1,"price":32248,"priceChange":-75.78,"quality":17.35,"qualityChange":-0.02},{"productId":363,"product":"Мяч","productName":"ball","volume":208400000,"volumeChange":-0.040999999999999995,"amount":20949,"amountChange":-0.04,"priceLevel":20.93,"sellers":6,"sellersChange":0,"divisions":34,"divisionsChange":0,"competition":1,"price":9939,"priceChange":-19.87,"quality":16.66,"qualityChange":0.06},{"productId":357,"product":"Надувной матрас","productName":"mattress","volume":183930000,"volumeChange":-0.039,"amount":63947,"amountChange":-0.038,"priceLevel":88.39,"sellers":6,"sellersChange":0,"divisions":45,"divisionsChange":0,"competition":1,"price":2874,"priceChange":-1.12,"quality":15.85,"qualityChange":-0.01},{"productId":352,"product":"Палатка","productName":"tent","volume":241620000,"volumeChange":-0.04,"amount":6006,"amountChange":-0.039,"priceLevel":64.68,"sellers":8,"sellersChange":0,"divisions":57,"divisionsChange":0,"competition":1,"price":40224,"priceChange":-24.58,"quality":17.11,"qualityChange":-0.01},{"productId":364,"product":"Ракетки","productName":"rackets","volume":145800000,"volumeChange":-0.045,"amount":16202,"amountChange":-0.047,"priceLevel":57.46,"sellers":6,"sellersChange":0,"divisions":47,"divisionsChange":0,"competition":1,"price":9000,"priceChange":20.22,"quality":16.92,"qualityChange":0.02},{"productId":355,"product":"Резиновая лодка","productName":"rubberboat","volume":223200000,"volumeChange":-0.047,"amount":3313,"amountChange":-0.046,"priceLevel":38.98,"sellers":8,"sellersChange":0,"divisions":57,"divisionsChange":0,"competition":2,"price":67317,"priceChange":-88.79,"quality":17.27,"qualityChange":0.02},{"productId":359,"product":"Роликовые коньки","productName":"roller","volume":249670000,"volumeChange":-0.102,"amount":14095,"amountChange":-0.09699999999999999,"priceLevel":64.08,"sellers":7,"sellersChange":0,"divisions":77,"divisionsChange":0,"competition":1,"price":17651,"priceChange":-93.21,"quality":17.61,"qualityChange":0.18},{"productId":354,"product":"Рюкзак","productName":"backpack","volume":238400000,"volumeChange":0.48,"amount":11571,"amountChange":0.442,"priceLevel":43.86,"sellers":8,"sellersChange":1,"divisions":55,"divisionsChange":12,"competition":1,"price":20632,"priceChange":1258.61,"quality":17.38,"qualityChange":1.25},{"productId":322,"product":"Солнечные очки","productName":"sunglasses","volume":98060000,"volumeChange":-0.034,"amount":25930,"amountChange":-0.048,"priceLevel":39.38,"sellers":5,"sellersChange":0,"divisions":22,"divisionsChange":0,"competition":1,"price":3804,"priceChange":66.76,"quality":15.01,"qualityChange":0},{"productId":353,"product":"Спальный мешок","productName":"sleeping","volume":241580000,"volumeChange":-0.039,"amount":11062,"amountChange":-0.038,"priceLevel":51.67,"sellers":8,"sellersChange":0,"divisions":58,"divisionsChange":0,"competition":1,"price":21841,"priceChange":-12.94,"quality":17.62,"qualityChange":0},{"productId":145,"product":"Спортивная одежда","productName":"sportclothes","volume":137420000,"volumeChange":-0.023,"amount":10852,"amountChange":-0.021,"priceLevel":77.2,"sellers":5,"sellersChange":0,"divisions":42,"divisionsChange":0,"competition":1,"price":12657,"priceChange":-19.04,"quality":15.68,"qualityChange":0.08},{"productId":444,"product":"Спортивное питание","productName":"nutrition","volume":249020000,"volumeChange":-0.033,"amount":78495,"amountChange":-0.028999999999999998,"priceLevel":35.24,"sellers":7,"sellersChange":0,"divisions":54,"divisionsChange":0,"competition":1,"price":3166,"priceChange":-13,"quality":18.13,"qualityChange":0.11},{"productId":415,"product":"Термос","productName":"thermos","volume":278650000,"volumeChange":-0.031,"amount":88958,"amountChange":-0.026000000000000002,"priceLevel":39.41,"sellers":10,"sellersChange":0,"divisions":84,"divisionsChange":0,"competition":2,"price":3125,"priceChange":-18.99,"quality":17.5,"qualityChange":0.1},{"productId":356,"product":"Топор","productName":"axe","volume":302510000,"volumeChange":-0.016,"amount":79885,"amountChange":-0.019,"priceLevel":45.03,"sellers":8,"sellersChange":0,"divisions":57,"divisionsChange":0,"competition":1,"price":3789,"priceChange":5.36,"quality":17.18,"qualityChange":0.03},{"productId":349,"product":"Тренажер","productName":"training","volume":217680000,"volumeChange":-0.05,"amount":1460,"amountChange":-0.049,"priceLevel":48.95,"sellers":7,"sellersChange":0,"divisions":54,"divisionsChange":0,"competition":1,"price":149061,"priceChange":-229.22,"quality":17.08,"qualityChange":-0.03},{"productId":443,"product":"Удочка","productName":"rod","volume":247460000,"volumeChange":-0.040999999999999995,"amount":29142,"amountChange":-0.037000000000000005,"priceLevel":52.92,"sellers":8,"sellersChange":0,"divisions":56,"divisionsChange":0,"competition":1,"price":8480,"priceChange":-45.17,"quality":16.95,"qualityChange":-0.08},{"productId":413,"product":"Фонарь","productName":"flashlight","volume":322020000,"volumeChange":0.22,"amount":56664,"amountChange":0.20600000000000002,"priceLevel":29.06,"sellers":10,"sellersChange":2,"divisions":84,"divisionsChange":11,"competition":2,"price":5685,"priceChange":75.03,"quality":17.94,"qualityChange":0.26},{"productId":406,"product":"Шлем","productName":"helmet","volume":279180000,"volumeChange":-0.032,"amount":21210,"amountChange":-0.033,"priceLevel":56.6,"sellers":8,"sellersChange":0,"divisions":81,"divisionsChange":0,"competition":2,"price":13147,"priceChange":8.97,"quality":17.84,"qualityChange":0.06},{"productId":360,"product":"Электросамокат","productName":"kickscooter","volume":254050000,"volumeChange":-0.044000000000000004,"amount":4845,"amountChange":-0.043,"priceLevel":58.57,"sellers":7,"sellersChange":0,"divisions":56,"divisionsChange":0,"competition":1,"price":52247,"priceChange":-181.96,"quality":17.68,"qualityChange":0.02}]},{"groupId":14,"group":"Детские товары","groupName":"childgoods","turnover":3830000000,"turnoverChange":-0.024,"share":0.0444,"margin":1.59,"competition":1,"priceLevel":55,"products":[{"productId":432,"product":"Бутылочка","productName":"bottle","volume":369760000,"volumeChange":-0.031,"amount":403022,"amountChange":-0.032,"priceLevel":87.64,"sellers":9,"sellersChange":0,"divisions":81,"divisionsChange":0,"competition":1,"price":918,"priceChange":-0.85,"quality":16.07,"qualityChange":-0.01},{"productId":139,"product":"Детская обувь","productName":"childshoes","volume":323140000,"volumeChange":-0.027999999999999997,"amount":71454,"amountChange":-0.027000000000000003,"priceLevel":39.31,"sellers":8,"sellersChange":0,"divisions":93,"divisionsChange":0,"competition":2,"price":4520,"priceChange":-3.97,"quality":19.1,"qualityChange":0.01},{"productId":144,"product":"Детская одежда","productName":"childclothes","volume":306120000,"volumeChange":-0.036000000000000004,"amount":63490,"amountChange":-0.042,"priceLevel":50.88,"sellers":8,"sellersChange":0,"divisions":97,"divisionsChange":0,"competition":1,"price":4822,"priceChange":0.03,"quality":19,"qualityChange":0},{"productId":417,"product":"Детская смесь","productName":"babyfood","volume":207140000,"volumeChange":0.172,"amount":38652,"amountChange":0.166,"priceLevel":83.08,"sellers":7,"sellersChange":1,"divisions":63,"divisionsChange":3,"competition":1,"price":5358,"priceChange":26.5,"quality":16.97,"qualityChange":0.08},{"productId":425,"product":"Детские книги","productName":"books","volume":176600000,"volumeChange":-0.017,"amount":92717,"amountChange":-0.013000000000000001,"priceLevel":44.02,"sellers":6,"sellersChange":0,"divisions":59,"divisionsChange":0,"competition":1,"price":1904,"priceChange":-11.06,"quality":18.14,"qualityChange":-0.06},{"productId":426,"product":"Канцтовары","productName":"stationery","volume":264320000,"volumeChange":-0.08900000000000001,"amount":61091,"amountChange":-0.095,"priceLevel":54.36,"sellers":8,"sellersChange":0,"divisions":78,"divisionsChange":0,"competition":1,"price":4322,"priceChange":19.26,"quality":18.87,"qualityChange":0.22},{"productId":424,"product":"Коляска","productName":"stroller","volume":236330000,"volumeChange":-0.039,"amount":3426,"amountChange":-0.043,"priceLevel":45.32,"sellers":7,"sellersChange":0,"divisions":89,"divisionsChange":0,"competition":2,"price":69023,"priceChange":97.71,"quality":17.67,"qualityChange":-0.02},{"productId":377,"product":"Конструктор","productName":"constructor","volume":193120000,"volumeChange":0.003,"amount":38096,"amountChange":-0.01,"priceLevel":64.67,"sellers":7,"sellersChange":0,"divisions":62,"divisionsChange":0,"competition":1,"price":5071,"priceChange":14.63,"quality":17.76,"qualityChange":0.05},{"productId":427,"product":"Кукла","productName":"doll","volume":233940000,"volumeChange":-0.024,"amount":11864,"amountChange":-0.022000000000000002,"priceLevel":69.43,"sellers":8,"sellersChange":0,"divisions":69,"divisionsChange":0,"competition":1,"price":19736,"priceChange":20.62,"quality":17.52,"qualityChange":-0.07},{"productId":431,"product":"Мебель для детей","productName":"furniture","volume":306130000,"volumeChange":-0.035,"amount":8124,"amountChange":-0.035,"priceLevel":20.47,"sellers":8,"sellersChange":0,"divisions":78,"divisionsChange":0,"competition":2,"price":37667,"priceChange":-16.95,"quality":19.38,"qualityChange":0},{"productId":121,"product":"Мягкая игрушка","productName":"toys","volume":268670000,"volumeChange":-0.031,"amount":59984,"amountChange":-0.035,"priceLevel":72.02,"sellers":8,"sellersChange":0,"divisions":74,"divisionsChange":0,"competition":1,"price":4472,"priceChange":17.67,"quality":18.01,"qualityChange":0.26},{"productId":429,"product":"Настольные игры","productName":"boardgames","volume":192490000,"volumeChange":-0.033,"amount":31006,"amountChange":-0.034,"priceLevel":40.65,"sellers":7,"sellersChange":1,"divisions":67,"divisionsChange":2,"competition":1,"price":6209,"priceChange":-1.39,"quality":19.32,"qualityChange":0},{"productId":423,"product":"Подгузники","productName":"diapers","volume":328750000,"volumeChange":-0.016,"amount":88517,"amountChange":-0.013000000000000001,"priceLevel":52.33,"sellers":8,"sellersChange":0,"divisions":85,"divisionsChange":0,"competition":2,"price":3712,"priceChange":-9.44,"quality":16.15,"qualityChange":0},{"productId":430,"product":"Тетрадь","productName":"exercisebook","volume":189160000,"volumeChange":-0.027999999999999997,"amount":454003,"amountChange":-0.028999999999999998,"priceLevel":36.63,"sellers":7,"sellersChange":0,"divisions":54,"divisionsChange":0,"competition":1,"price":416,"priceChange":-0.19,"quality":18.52,"qualityChange":0},{"productId":428,"product":"Трансформер","productName":"transformer","volume":229620000,"volumeChange":-0.042,"amount":30973,"amountChange":-0.042,"priceLevel":58.08,"sellers":7,"sellersChange":0,"divisions":90,"divisionsChange":0,"competition":2,"price":7414,"priceChange":10.63,"quality":17.71,"qualityChange":0.01}]},{"groupId":6,"group":"Автомобильные товары","groupName":"automotive","turnover":4750000000,"turnoverChange":-0.035,"share":0.055,"margin":1.34,"competition":0,"priceLevel":46.45,"products":[{"productId":159,"product":"Автомобиль","productName":"car","volume":229230000,"volumeChange":-0.065,"amount":72,"amountChange":-0.065,"priceLevel":48.3,"sellers":7,"sellersChange":0,"divisions":82,"divisionsChange":0,"competition":0,"price":3183269,"priceChange":-611.25,"quality":18.19,"qualityChange":0.07},{"productId":422,"product":"Аккумулятор","productName":"batterypack","volume":230920000,"volumeChange":-0.006,"amount":8634,"amountChange":-0.006,"priceLevel":40.16,"sellers":6,"sellersChange":0,"divisions":47,"divisionsChange":0,"competition":0,"price":26744,"priceChange":13.12,"quality":18.63,"qualityChange":0},{"productId":398,"product":"Аксессуары","productName":"accessories","volume":292660000,"volumeChange":-0.001,"amount":79404,"amountChange":-0.004,"priceLevel":37.62,"sellers":7,"sellersChange":1,"divisions":52,"divisionsChange":5,"competition":0,"price":3687,"priceChange":33.66,"quality":19.8,"qualityChange":0.1},{"productId":399,"product":"Домкрат","productName":"jack","volume":472810000,"volumeChange":-0.040999999999999995,"amount":76449,"amountChange":-0.040999999999999995,"priceLevel":67.96,"sellers":7,"sellersChange":0,"divisions":84,"divisionsChange":0,"competition":1,"price":6186,"priceChange":2.19,"quality":18.97,"qualityChange":0.01},{"productId":383,"product":"Квадроцикл","productName":"quadbike","volume":316300000,"volumeChange":-0.049,"amount":269,"amountChange":-0.049,"priceLevel":43.09,"sellers":7,"sellersChange":0,"divisions":85,"divisionsChange":0,"competition":1,"price":1176297,"priceChange":117.38,"quality":18.27,"qualityChange":0.04},{"productId":44,"product":"Комплектующие","productName":"parts","volume":429300000,"volumeChange":-0.037000000000000005,"amount":104027,"amountChange":-0.037000000000000005,"priceLevel":63.73,"sellers":5,"sellersChange":0,"divisions":82,"divisionsChange":0,"competition":1,"price":4128,"priceChange":-0.72,"quality":17.54,"qualityChange":-0.04},{"productId":315,"product":"Компрессор","productName":"compressor","volume":389380000,"volumeChange":-0.039,"amount":79088,"amountChange":-0.039,"priceLevel":70,"sellers":7,"sellersChange":0,"divisions":83,"divisionsChange":0,"competition":1,"price":4926,"priceChange":0.62,"quality":18.24,"qualityChange":0},{"productId":376,"product":"Кузовные детали","productName":"bodyparts","volume":200220000,"volumeChange":0.055,"amount":1801,"amountChange":0.059000000000000004,"priceLevel":25.46,"sellers":7,"sellersChange":0,"divisions":50,"divisionsChange":0,"competition":1,"price":110795,"priceChange":-857.69,"quality":19.3,"qualityChange":0.61},{"productId":236,"product":"Машинное масло","productName":"machineoil","volume":236170000,"volumeChange":-0.032,"amount":23620,"amountChange":-0.032,"priceLevel":21.99,"sellers":7,"sellersChange":0,"divisions":51,"divisionsChange":0,"competition":1,"price":9951,"priceChange":-5.23,"quality":17.68,"qualityChange":0.05},{"productId":160,"product":"Мотоцикл","productName":"moto","volume":383080000,"volumeChange":-0.05,"amount":248,"amountChange":-0.05,"priceLevel":69.24,"sellers":6,"sellersChange":0,"divisions":87,"divisionsChange":0,"competition":1,"price":1545253,"priceChange":-568.13,"quality":18.87,"qualityChange":0},{"productId":314,"product":"Омывающая жидкость","productName":"washerfluid","volume":455670000,"volumeChange":-0.027000000000000003,"amount":147439,"amountChange":-0.027999999999999997,"priceLevel":47.62,"sellers":4,"sellersChange":0,"divisions":74,"divisionsChange":0,"competition":1,"price":3092,"priceChange":1.66,"quality":20.13,"qualityChange":0.1},{"productId":400,"product":"Сабвуфер","productName":"subwoofer","volume":353840000,"volumeChange":-0.07200000000000001,"amount":5805,"amountChange":-0.073,"priceLevel":29.64,"sellers":7,"sellersChange":0,"divisions":82,"divisionsChange":0,"competition":1,"price":60953,"priceChange":-36.21,"quality":21.51,"qualityChange":0.61},{"productId":346,"product":"Скутер","productName":"scooter","volume":137810000,"volumeChange":-0.040999999999999995,"amount":279,"amountChange":-0.040999999999999995,"priceLevel":32.9,"sellers":7,"sellersChange":0,"divisions":50,"divisionsChange":0,"competition":1,"price":494045,"priceChange":152.44,"quality":19.89,"qualityChange":-0.05},{"productId":161,"product":"Шины","productName":"tire","volume":412310000,"volumeChange":-0.036000000000000004,"amount":16943,"amountChange":-0.039,"priceLevel":18.89,"sellers":6,"sellersChange":0,"divisions":88,"divisionsChange":0,"competition":1,"price":24339,"priceChange":24.46,"quality":19.57,"qualityChange":0.17},{"productId":378,"product":"Электромобиль","productName":"electriccar","volume":207850000,"volumeChange":-0.04,"amount":46,"amountChange":-0.042,"priceLevel":35.82,"sellers":5,"sellersChange":-1,"divisions":82,"divisionsChange":-6,"competition":1,"price":4509212,"priceChange":-10114.5,"quality":20.26,"qualityChange":-0.03}]},{"groupId":8,"group":"Предметы роскоши","groupName":"luxury","turnover":2180000000,"turnoverChange":-0.064,"share":0.0253,"margin":1.59,"competition":0,"priceLevel":63.13,"products":[{"productId":437,"product":"Арома-палочки","productName":"aroma","volume":208700000,"volumeChange":-0.174,"amount":116158,"amountChange":-0.152,"priceLevel":80.95,"sellers":5,"sellersChange":-1,"divisions":71,"divisionsChange":-18,"competition":1,"price":1779,"priceChange":-64.44,"quality":17.96,"qualityChange":-0.26},{"productId":209,"product":"Белье","productName":"underwear","volume":127860000,"volumeChange":0.026000000000000002,"amount":40980,"amountChange":0.013999999999999999,"priceLevel":67.81,"sellers":2,"sellersChange":0,"divisions":23,"divisionsChange":0,"competition":1,"price":3147,"priceChange":64.88,"quality":20.63,"qualityChange":0.18},{"productId":321,"product":"Бижутерия","productName":"bijouterie","volume":142380000,"volumeChange":0.006999999999999999,"amount":36483,"amountChange":0.01,"priceLevel":62.63,"sellers":4,"sellersChange":1,"divisions":40,"divisionsChange":6,"competition":1,"price":3907,"priceChange":-9.12,"quality":16.38,"qualityChange":0.13},{"productId":325,"product":"Бритва","productName":"razor","volume":43440000,"volumeChange":0.591,"amount":7386,"amountChange":0.5820000000000001,"priceLevel":42.83,"sellers":1,"sellersChange":-1,"divisions":5,"divisionsChange":-18,"competition":1,"price":6500,"priceChange":926.89,"quality":20.47,"qualityChange":3.3},{"productId":152,"product":"Золотые часы","productName":"watches","volume":219600000,"volumeChange":-0.021,"amount":953,"amountChange":-0.022000000000000002,"priceLevel":39.39,"sellers":6,"sellersChange":0,"divisions":88,"divisionsChange":0,"competition":1,"price":230723,"priceChange":479.98,"quality":16.7,"qualityChange":0.01},{"productId":405,"product":"Колготки","productName":"tights","volume":11090000,"volumeChange":-0.01,"amount":5687,"amountChange":-0.01,"priceLevel":51.85,"sellers":1,"sellersChange":0,"divisions":5,"divisionsChange":0,"competition":1,"price":1950,"priceChange":0,"quality":17.17,"qualityChange":0.21},{"productId":382,"product":"Косметика","productName":"makeup","volume":136610000,"volumeChange":-0.046,"amount":57910,"amountChange":-0.051,"priceLevel":67.1,"sellers":2,"sellersChange":0,"divisions":23,"divisionsChange":0,"competition":1,"price":2333,"priceChange":-15.16,"quality":19.5,"qualityChange":-0.08},{"productId":438,"product":"Массажер","productName":"massager","volume":124200000,"volumeChange":-0.045,"amount":3277,"amountChange":-0.045,"priceLevel":37.73,"sellers":5,"sellersChange":0,"divisions":69,"divisionsChange":0,"competition":1,"price":37900,"priceChange":1.6,"quality":19.45,"qualityChange":0.06},{"productId":170,"product":"Парфюмерия","productName":"parfume","volume":201570000,"volumeChange":-0.278,"amount":10046,"amountChange":-0.264,"priceLevel":72.57,"sellers":5,"sellersChange":-1,"divisions":71,"divisionsChange":-18,"competition":1,"price":19954,"priceChange":-484.61,"quality":17.46,"qualityChange":-0.19},{"productId":347,"product":"Сувенир","productName":"souvenir","volume":119260000,"volumeChange":0.027999999999999997,"amount":6286,"amountChange":0.019,"priceLevel":100,"sellers":2,"sellersChange":0,"divisions":24,"divisionsChange":0,"competition":0,"price":18907,"priceChange":192.54,"quality":15.5,"qualityChange":0.45},{"productId":147,"product":"Сумка","productName":"bag","volume":166930000,"volumeChange":-0.043,"amount":8294,"amountChange":-0.043,"priceLevel":63.48,"sellers":5,"sellersChange":0,"divisions":70,"divisionsChange":0,"competition":1,"price":20127,"priceChange":2.89,"quality":18.73,"qualityChange":0.09},{"productId":403,"product":"Фен","productName":"hairdryer","volume":191750000,"volumeChange":-0.05,"amount":21719,"amountChange":-0.05,"priceLevel":78.84,"sellers":5,"sellersChange":0,"divisions":70,"divisionsChange":0,"competition":1,"price":8829,"priceChange":0.8,"quality":19.3,"qualityChange":0.14},{"productId":402,"product":"Цветы","productName":"flowers","volume":143660000,"volumeChange":-0.027000000000000003,"amount":93943,"amountChange":-0.027000000000000003,"priceLevel":46.68,"sellers":5,"sellersChange":0,"divisions":69,"divisionsChange":0,"competition":1,"price":1529,"priceChange":0.09,"quality":22.13,"qualityChange":0.03},{"productId":404,"product":"Эпилятор","productName":"epilator","volume":160280000,"volumeChange":-0.048,"amount":36701,"amountChange":-0.048,"priceLevel":45.67,"sellers":5,"sellersChange":0,"divisions":69,"divisionsChange":0,"competition":1,"price":4367,"priceChange":1.04,"quality":19.51,"qualityChange":-0.11},{"productId":166,"product":"Ювелирные украшения","productName":"jewelry","volume":183500000,"volumeChange":-0.027000000000000003,"amount":805,"amountChange":-0.027999999999999997,"priceLevel":65.17,"sellers":5,"sellersChange":0,"divisions":58,"divisionsChange":0,"competition":0,"price":228183,"priceChange":528.09,"quality":16.56,"qualityChange":0}]},{"groupId":11,"group":"Рестораны","groupName":"restaurant","turnover":4290000000,"turnoverChange":-0.008,"share":0.049800000000000004,"margin":0,"competition":2,"priceLevel":52.61,"products":[{"productId":275,"product":"Борщ","productName":"borcht","volume":273910000,"volumeChange":-0.004,"amount":1344660,"amountChange":-0.003,"priceLevel":91.55,"sellers":7,"sellersChange":0,"divisions":156,"divisionsChange":0,"competition":3,"price":204,"priceChange":-0.03,"quality":19.04,"qualityChange":0.01},{"productId":294,"product":"Винегрет","productName":"venigret","volume":208970000,"volumeChange":-0.03,"amount":1652495,"amountChange":-0.031,"priceLevel":86.38,"sellers":4,"sellersChange":-1,"divisions":129,"divisionsChange":-12,"competition":3,"price":126,"priceChange":-0.58,"quality":19.42,"qualityChange":0.16},{"productId":296,"product":"Гамбургер","productName":"hamburger","volume":369070000,"volumeChange":0.012,"amount":617170,"amountChange":0.013000000000000001,"priceLevel":42.59,"sellers":11,"sellersChange":0,"divisions":228,"divisionsChange":0,"competition":2,"price":598,"priceChange":-0.23,"quality":18.27,"qualityChange":0.06},{"productId":392,"product":"Глинтвейн","productName":"alkococteil","volume":139960000,"volumeChange":-0.024,"amount":116982,"amountChange":-0.024,"priceLevel":45.73,"sellers":9,"sellersChange":0,"divisions":102,"divisionsChange":0,"competition":2,"price":1196,"priceChange":-0.17,"quality":18.66,"qualityChange":-0.03},{"productId":286,"product":"Жареная рыба","productName":"friedfish","volume":178990000,"volumeChange":0,"amount":225540,"amountChange":0,"priceLevel":28.5,"sellers":7,"sellersChange":0,"divisions":132,"divisionsChange":0,"competition":2,"price":794,"priceChange":0,"quality":19.51,"qualityChange":0.05},{"productId":389,"product":"Запеканка","productName":"frenchfries","volume":201110000,"volumeChange":0,"amount":719871,"amountChange":0.001,"priceLevel":59.39,"sellers":7,"sellersChange":0,"divisions":67,"divisionsChange":0,"competition":1,"price":279,"priceChange":-0.46,"quality":17.54,"qualityChange":0.04},{"productId":385,"product":"Итальянское ассорти","productName":"potatomeat","volume":255510000,"volumeChange":-0.005,"amount":329530,"amountChange":-0.005,"priceLevel":33.85,"sellers":11,"sellersChange":0,"divisions":162,"divisionsChange":0,"competition":2,"price":775,"priceChange":-0.23,"quality":19.03,"qualityChange":0},{"productId":393,"product":"Молочный коктейль","productName":"juicecocteil","volume":27900000,"volumeChange":-0.034,"amount":86097,"amountChange":-0.034,"priceLevel":100,"sellers":1,"sellersChange":0,"divisions":16,"divisionsChange":0,"competition":1,"price":324,"priceChange":0,"quality":17.4,"qualityChange":0},{"productId":283,"product":"Мясо по-французски","productName":"frenchmeat","volume":239230000,"volumeChange":-0.019,"amount":190540,"amountChange":-0.026000000000000002,"priceLevel":33.2,"sellers":10,"sellersChange":-1,"divisions":165,"divisionsChange":-8,"competition":2,"price":1258,"priceChange":4.01,"quality":18.41,"qualityChange":0.07},{"productId":390,"product":"Пивной сет","productName":"nuggets","volume":181290000,"volumeChange":0.017,"amount":114367,"amountChange":0.017,"priceLevel":28.74,"sellers":10,"sellersChange":0,"divisions":121,"divisionsChange":0,"competition":1,"price":1585,"priceChange":-2.27,"quality":18.92,"qualityChange":0.03},{"productId":298,"product":"Пицца","productName":"pizza","volume":341420000,"volumeChange":0.011000000000000001,"amount":474663,"amountChange":0.012,"priceLevel":40.99,"sellers":14,"sellersChange":0,"divisions":264,"divisionsChange":0,"competition":3,"price":714,"priceChange":-0.76,"quality":17.84,"qualityChange":0.08},{"productId":284,"product":"Плов","productName":"pilaf","volume":234130000,"volumeChange":-0.005,"amount":541513,"amountChange":-0.004,"priceLevel":61.38,"sellers":10,"sellersChange":0,"divisions":162,"divisionsChange":0,"competition":4,"price":432,"priceChange":-0.09,"quality":17.46,"qualityChange":0.08},{"productId":386,"product":"Ребрышки по-фламандски","productName":"ase","volume":313390000,"volumeChange":-0.04,"amount":609970,"amountChange":-0.044000000000000004,"priceLevel":57.76,"sellers":9,"sellersChange":-1,"divisions":116,"divisionsChange":-8,"competition":2,"price":514,"priceChange":0.77,"quality":18.24,"qualityChange":0.08},{"productId":293,"product":"Салат Греческий","productName":"saladgreece","volume":141270000,"volumeChange":-0.004,"amount":290464,"amountChange":-0.003,"priceLevel":34.63,"sellers":6,"sellersChange":-1,"divisions":127,"divisionsChange":-10,"competition":2,"price":485,"priceChange":-2.79,"quality":19.21,"qualityChange":0.11},{"productId":290,"product":"Салат Столичный","productName":"saladcapital","volume":305450000,"volumeChange":-0.005,"amount":647425,"amountChange":-0.004,"priceLevel":55.26,"sellers":8,"sellersChange":0,"divisions":165,"divisionsChange":0,"competition":3,"price":467,"priceChange":-0.46,"quality":19.11,"qualityChange":0.01},{"productId":388,"product":"Сельдь под шубой","productName":"saladceasar","volume":147070000,"volumeChange":-0.02,"amount":162689,"amountChange":-0.018000000000000002,"priceLevel":48.85,"sellers":4,"sellersChange":0,"divisions":54,"divisionsChange":0,"competition":1,"price":904,"priceChange":-0.94,"quality":19.59,"qualityChange":0},{"productId":391,"product":"Сидр","productName":"compote","volume":165290000,"volumeChange":-0.02,"amount":363507,"amountChange":-0.019,"priceLevel":46.73,"sellers":4,"sellersChange":0,"divisions":85,"divisionsChange":0,"competition":2,"price":455,"priceChange":-0.17,"quality":19.14,"qualityChange":0.02},{"productId":276,"product":"Солянка","productName":"saltwort","volume":241830000,"volumeChange":-0.025,"amount":343008,"amountChange":-0.024,"priceLevel":61.85,"sellers":6,"sellersChange":-1,"divisions":127,"divisionsChange":-12,"competition":2,"price":695,"priceChange":-7.24,"quality":18.36,"qualityChange":-0.01},{"productId":302,"product":"Шаурма","productName":"shawarma","volume":238750000,"volumeChange":0.019,"amount":685137,"amountChange":0.027000000000000003,"priceLevel":50.57,"sellers":12,"sellersChange":0,"divisions":202,"divisionsChange":0,"competition":2,"price":349,"priceChange":-0.35,"quality":19.23,"qualityChange":0.04},{"productId":387,"product":"Штрудель","productName":"schnitzel","volume":87800000,"volumeChange":-0.032,"amount":430491,"amountChange":-0.031,"priceLevel":100,"sellers":5,"sellersChange":0,"divisions":95,"divisionsChange":0,"competition":1,"price":204,"priceChange":0,"quality":17.68,"qualityChange":0.02}]}],"date":1774244897950}