{"cityId":38,"groups":[{"groupId":1,"group":"Продукты питания","groupName":"food","turnover":10250000000,"turnoverChange":0.02,"share":0.1618,"margin":1.78,"competition":3,"priceLevel":65.06,"products":[{"productId":90,"product":"Вино","productName":"wine","volume":293080000,"volumeChange":0.046,"amount":157694,"amountChange":0.05,"priceLevel":43.52,"sellers":47,"sellersChange":0,"divisions":196,"divisionsChange":0,"competition":1,"price":1852,"priceChange":-9.59,"quality":5.6,"qualityChange":0},{"productId":251,"product":"Виноград","productName":"grape","volume":181140000,"volumeChange":-0.18100000000000002,"amount":690788,"amountChange":-0.12,"priceLevel":34.58,"sellers":50,"sellersChange":2,"divisions":220,"divisionsChange":7,"competition":3,"price":264,"priceChange":-18,"quality":6.33,"qualityChange":0.08},{"productId":84,"product":"Йогурт","productName":"yogurt","volume":379520000,"volumeChange":0.017,"amount":1183029,"amountChange":0.021,"priceLevel":90.9,"sellers":56,"sellersChange":0,"divisions":302,"divisionsChange":2,"competition":4,"price":320,"priceChange":-1.17,"quality":5.52,"qualityChange":0.03},{"productId":255,"product":"Картофель","productName":"potato","volume":352260000,"volumeChange":0.011000000000000001,"amount":3608674,"amountChange":0.008,"priceLevel":59.31,"sellers":51,"sellersChange":-2,"divisions":254,"divisionsChange":-5,"competition":3,"price":97.42,"priceChange":-0.72,"quality":6.6,"qualityChange":0.09},{"productId":78,"product":"Колбаса","productName":"sausages","volume":357690000,"volumeChange":0.02,"amount":198836,"amountChange":0.013000000000000001,"priceLevel":93.05,"sellers":43,"sellersChange":1,"divisions":234,"divisionsChange":10,"competition":2,"price":1801,"priceChange":12.31,"quality":5.38,"qualityChange":0.03},{"productId":92,"product":"Крепкий алкоголь","productName":"vodka","volume":347450000,"volumeChange":0.044000000000000004,"amount":69052,"amountChange":0.04,"priceLevel":44.37,"sellers":55,"sellersChange":-2,"divisions":282,"divisionsChange":-6,"competition":3,"price":5035,"priceChange":22.3,"quality":5.9,"qualityChange":0.02},{"productId":87,"product":"Крупа","productName":"croup","volume":404390000,"volumeChange":0.003,"amount":1665672,"amountChange":0,"priceLevel":98.72,"sellers":56,"sellersChange":-1,"divisions":274,"divisionsChange":0,"competition":4,"price":242,"priceChange":0.15,"quality":5.96,"qualityChange":0.01},{"productId":80,"product":"Макаронные изделия","productName":"macaron","volume":388330000,"volumeChange":-0.003,"amount":2262385,"amountChange":0.006,"priceLevel":42.37,"sellers":52,"sellersChange":0,"divisions":270,"divisionsChange":1,"competition":5,"price":171,"priceChange":-1.26,"quality":5.89,"qualityChange":0.02},{"productId":238,"product":"Масло","productName":"butter","volume":307120000,"volumeChange":0.033,"amount":445153,"amountChange":0.031,"priceLevel":57.4,"sellers":46,"sellersChange":-3,"divisions":219,"divisionsChange":-7,"competition":4,"price":689,"priceChange":1.17,"quality":5.61,"qualityChange":0.03},{"productId":49,"product":"Молоко","productName":"milk","volume":383070000,"volumeChange":0.009000000000000001,"amount":2296569,"amountChange":0.005,"priceLevel":79.22,"sellers":54,"sellersChange":-1,"divisions":266,"divisionsChange":-9,"competition":2,"price":167,"priceChange":1.03,"quality":5.93,"qualityChange":0.11},{"productId":440,"product":"Морковь","productName":"carrot","volume":377150000,"volumeChange":0.026000000000000002,"amount":4342636,"amountChange":0.027000000000000003,"priceLevel":82.97,"sellers":54,"sellersChange":-3,"divisions":267,"divisionsChange":-2,"competition":3,"price":86.76,"priceChange":-0.11,"quality":8.21,"qualityChange":0.01},{"productId":86,"product":"Мука","productName":"flour","volume":377510000,"volumeChange":0.006,"amount":2534543,"amountChange":-0.008,"priceLevel":88.86,"sellers":43,"sellersChange":1,"divisions":225,"divisionsChange":11,"competition":3,"price":149,"priceChange":0.72,"quality":5.9,"qualityChange":-0.02},{"productId":51,"product":"Мясо","productName":"meat","volume":345970000,"volumeChange":0.039,"amount":633623,"amountChange":0.042,"priceLevel":26.42,"sellers":60,"sellersChange":-1,"divisions":295,"divisionsChange":2,"competition":3,"price":546,"priceChange":-0.7,"quality":5.49,"qualityChange":-0.01},{"productId":441,"product":"Огурцы","productName":"cucumber","volume":229470000,"volumeChange":0.071,"amount":2082415,"amountChange":0.076,"priceLevel":64.74,"sellers":38,"sellersChange":-3,"divisions":179,"divisionsChange":-15,"competition":2,"price":110,"priceChange":-0.5,"quality":8.09,"qualityChange":0.03},{"productId":101,"product":"Печенье","productName":"cookies","volume":353200000,"volumeChange":0.036000000000000004,"amount":273126,"amountChange":0.031,"priceLevel":54.43,"sellers":46,"sellersChange":1,"divisions":249,"divisionsChange":2,"competition":3,"price":1292,"priceChange":3.04,"quality":5.54,"qualityChange":0.04},{"productId":89,"product":"Пиво","productName":"beer","volume":390420000,"volumeChange":0.011000000000000001,"amount":650618,"amountChange":0.018000000000000002,"priceLevel":79.83,"sellers":56,"sellersChange":-1,"divisions":290,"divisionsChange":-1,"competition":4,"price":597,"priceChange":-5.71,"quality":5.93,"qualityChange":0},{"productId":442,"product":"Помидоры","productName":"tomato","volume":251970000,"volumeChange":0.055999999999999994,"amount":1002743,"amountChange":0.053,"priceLevel":81.93,"sellers":46,"sellersChange":-1,"divisions":189,"divisionsChange":-2,"competition":4,"price":252,"priceChange":0.74,"quality":7.93,"qualityChange":0},{"productId":94,"product":"Прохладительные напитки","productName":"gaswater","volume":362530000,"volumeChange":0.003,"amount":1146433,"amountChange":0.004,"priceLevel":94.03,"sellers":48,"sellersChange":0,"divisions":228,"divisionsChange":4,"competition":3,"price":316,"priceChange":-0.28,"quality":5.89,"qualityChange":0.03},{"productId":50,"product":"Растительное масло","productName":"fat","volume":387670000,"volumeChange":-0.001,"amount":1048958,"amountChange":-0.004,"priceLevel":60.28,"sellers":53,"sellersChange":0,"divisions":264,"divisionsChange":1,"competition":3,"price":369,"priceChange":0.87,"quality":5.87,"qualityChange":0.04},{"productId":56,"product":"Рыба","productName":"fish","volume":309570000,"volumeChange":0.059000000000000004,"amount":186800,"amountChange":0.057,"priceLevel":23.62,"sellers":55,"sellersChange":1,"divisions":249,"divisionsChange":6,"competition":2,"price":1658,"priceChange":12.1,"quality":6.18,"qualityChange":0.07},{"productId":57,"product":"Сахар","productName":"sugar","volume":389160000,"volumeChange":0.012,"amount":1702843,"amountChange":0.022000000000000002,"priceLevel":94.81,"sellers":41,"sellersChange":0,"divisions":231,"divisionsChange":2,"competition":3,"price":218,"priceChange":-13.63,"quality":5.79,"qualityChange":0.11},{"productId":260,"product":"Свекла","productName":"beet","volume":361200000,"volumeChange":-0.016,"amount":4399271,"amountChange":0.01,"priceLevel":58.44,"sellers":49,"sellersChange":-1,"divisions":234,"divisionsChange":-3,"competition":3,"price":82.74,"priceChange":0.32,"quality":5.94,"qualityChange":-0.1},{"productId":95,"product":"Сок","productName":"juice","volume":315620000,"volumeChange":0.053,"amount":829340,"amountChange":0.045,"priceLevel":23.04,"sellers":48,"sellersChange":1,"divisions":204,"divisionsChange":1,"competition":2,"price":380,"priceChange":1.14,"quality":5.64,"qualityChange":0.01},{"productId":83,"product":"Сыр","productName":"cheese","volume":343880000,"volumeChange":0.022000000000000002,"amount":109400,"amountChange":0.032,"priceLevel":80.41,"sellers":46,"sellersChange":2,"divisions":221,"divisionsChange":11,"competition":3,"price":3136,"priceChange":-32.1,"quality":5.41,"qualityChange":0.01},{"productId":102,"product":"Торт","productName":"cake","volume":342110000,"volumeChange":0.043,"amount":103266,"amountChange":0.044000000000000004,"priceLevel":59.46,"sellers":47,"sellersChange":-1,"divisions":206,"divisionsChange":0,"competition":3,"price":3322,"priceChange":8.62,"quality":5.9,"qualityChange":0.02},{"productId":312,"product":"Фрукты","productName":"fruits","volume":315810000,"volumeChange":0.11800000000000001,"amount":1045715,"amountChange":0.096,"priceLevel":44.64,"sellers":42,"sellersChange":0,"divisions":165,"divisionsChange":-1,"competition":3,"price":302,"priceChange":0.87,"quality":7.18,"qualityChange":0.05},{"productId":99,"product":"Хлеб","productName":"bread","volume":371740000,"volumeChange":0.013000000000000001,"amount":1742664,"amountChange":0.008,"priceLevel":100,"sellers":44,"sellersChange":1,"divisions":235,"divisionsChange":7,"competition":4,"price":213,"priceChange":0.48,"quality":5.87,"qualityChange":0},{"productId":103,"product":"Шоколад","productName":"chocolate","volume":368800000,"volumeChange":0.006999999999999999,"amount":701990,"amountChange":-0.001,"priceLevel":42.32,"sellers":48,"sellersChange":1,"divisions":288,"divisionsChange":11,"competition":3,"price":528,"priceChange":3.92,"quality":5.9,"qualityChange":0.01},{"productId":250,"product":"Яблоки","productName":"apples","volume":284760000,"volumeChange":0.049,"amount":3079148,"amountChange":0.051,"priceLevel":22.2,"sellers":35,"sellersChange":-3,"divisions":165,"divisionsChange":-12,"competition":2,"price":92.78,"priceChange":0.33,"quality":6.66,"qualityChange":-0.03},{"productId":72,"product":"Яйца","productName":"eggs","volume":381400000,"volumeChange":0.016,"amount":1331982,"amountChange":0.008,"priceLevel":74.71,"sellers":58,"sellersChange":2,"divisions":288,"divisionsChange":6,"competition":2,"price":286,"priceChange":0.34,"quality":5.28,"qualityChange":0.04}]},{"groupId":2,"group":"Товары для дома","groupName":"housegoods","turnover":5830000000,"turnoverChange":0.046,"share":0.092,"margin":1.76,"competition":4,"priceLevel":41.86,"products":[{"productId":375,"product":"Батарейка","productName":"battery","volume":234910000,"volumeChange":0.026000000000000002,"amount":415586,"amountChange":0.027000000000000003,"priceLevel":23.68,"sellers":30,"sellersChange":0,"divisions":103,"divisionsChange":0,"competition":4,"price":565,"priceChange":-0.93,"quality":5.93,"qualityChange":0},{"productId":17,"product":"Бумага","productName":"paper","volume":268430000,"volumeChange":0.052000000000000005,"amount":406872,"amountChange":0.05,"priceLevel":42.52,"sellers":35,"sellersChange":0,"divisions":153,"divisionsChange":-3,"competition":4,"price":658,"priceChange":0.17,"quality":5.7,"qualityChange":0.05},{"productId":131,"product":"Диван","productName":"sofa","volume":243990000,"volumeChange":0.07,"amount":1590,"amountChange":0.075,"priceLevel":78.21,"sellers":26,"sellersChange":0,"divisions":122,"divisionsChange":1,"competition":3,"price":153684,"priceChange":221.13,"quality":5.61,"qualityChange":0.09},{"productId":150,"product":"Зонт","productName":"umbrella","volume":201330000,"volumeChange":0.043,"amount":69262,"amountChange":0.042,"priceLevel":0.41,"sellers":28,"sellersChange":0,"divisions":105,"divisionsChange":0,"competition":4,"price":2909,"priceChange":5.35,"quality":6.09,"qualityChange":0},{"productId":108,"product":"Зубная паста","productName":"toothpaste","volume":248440000,"volumeChange":0.028999999999999998,"amount":1521404,"amountChange":0.034,"priceLevel":30.31,"sellers":36,"sellersChange":2,"divisions":220,"divisionsChange":5,"competition":6,"price":163,"priceChange":-1.27,"quality":5.58,"qualityChange":0.06},{"productId":452,"product":"Кастрюля","productName":"casserole","volume":220920000,"volumeChange":0.039,"amount":17462,"amountChange":0.035,"priceLevel":59.17,"sellers":24,"sellersChange":0,"divisions":93,"divisionsChange":0,"competition":3,"price":12729,"priceChange":126.73,"quality":6.14,"qualityChange":0.08},{"productId":451,"product":"Комод","productName":"dresser","volume":236490000,"volumeChange":0.040999999999999995,"amount":8262,"amountChange":0.046,"priceLevel":39.19,"sellers":27,"sellersChange":0,"divisions":107,"divisionsChange":0,"competition":4,"price":28618,"priceChange":-40.94,"quality":5.55,"qualityChange":0.02},{"productId":463,"product":"Кофемашина","productName":"coffeemachine","volume":205850000,"volumeChange":0.073,"amount":2498,"amountChange":0.065,"priceLevel":19.16,"sellers":27,"sellersChange":-1,"divisions":91,"divisionsChange":-5,"competition":4,"price":82574,"priceChange":430.77,"quality":6.33,"qualityChange":0.13},{"productId":132,"product":"Кресло","productName":"chair","volume":245910000,"volumeChange":0.084,"amount":4740,"amountChange":0.07400000000000001,"priceLevel":72.87,"sellers":29,"sellersChange":2,"divisions":135,"divisionsChange":10,"competition":4,"price":52046,"priceChange":733.31,"quality":5.51,"qualityChange":0.05},{"productId":135,"product":"Кровать","productName":"bed","volume":250680000,"volumeChange":0.084,"amount":6308,"amountChange":0.077,"priceLevel":71.09,"sellers":27,"sellersChange":0,"divisions":133,"divisionsChange":0,"competition":4,"price":39736,"priceChange":447.11,"quality":5.6,"qualityChange":0.07},{"productId":408,"product":"Кухонный гарнитур","productName":"kitchen","volume":229220000,"volumeChange":0.052000000000000005,"amount":1214,"amountChange":0.065,"priceLevel":58.1,"sellers":26,"sellersChange":1,"divisions":107,"divisionsChange":2,"competition":3,"price":187845,"priceChange":-3667.98,"quality":5.75,"qualityChange":0.03},{"productId":107,"product":"Моющее средство","productName":"detergent","volume":258690000,"volumeChange":0.023,"amount":142189,"amountChange":0.024,"priceLevel":52.78,"sellers":34,"sellersChange":0,"divisions":197,"divisionsChange":0,"competition":5,"price":1821,"priceChange":1.13,"quality":5.66,"qualityChange":0.07},{"productId":105,"product":"Мыло","productName":"soap","volume":222740000,"volumeChange":-0.013999999999999999,"amount":463592,"amountChange":-0.013999999999999999,"priceLevel":24.24,"sellers":34,"sellersChange":0,"divisions":208,"divisionsChange":-5,"competition":5,"price":480,"priceChange":-0.42,"quality":5.59,"qualityChange":0.05},{"productId":454,"product":"Полотенце","productName":"towel","volume":190390000,"volumeChange":0.027999999999999997,"amount":59501,"amountChange":0.022000000000000002,"priceLevel":29.33,"sellers":26,"sellersChange":0,"divisions":101,"divisionsChange":0,"competition":4,"price":3206,"priceChange":19.32,"quality":5.7,"qualityChange":0},{"productId":319,"product":"Постельные принадлежности","productName":"beddress","volume":148780000,"volumeChange":0.055999999999999994,"amount":50256,"amountChange":0.055,"priceLevel":0.44,"sellers":27,"sellersChange":1,"divisions":105,"divisionsChange":4,"competition":4,"price":2972,"priceChange":15.45,"quality":5.43,"qualityChange":0.02},{"productId":153,"product":"Посуда","productName":"dishes","volume":207320000,"volumeChange":0.057999999999999996,"amount":65673,"amountChange":0.04,"priceLevel":48.61,"sellers":27,"sellersChange":0,"divisions":107,"divisionsChange":0,"competition":4,"price":3233,"priceChange":116.83,"quality":5.3,"qualityChange":0.13},{"productId":373,"product":"Пылесос","productName":"cleaner","volume":263970000.00000003,"volumeChange":0.042,"amount":4470,"amountChange":0.04,"priceLevel":59.9,"sellers":38,"sellersChange":0,"divisions":151,"divisionsChange":0,"competition":4,"price":58977,"priceChange":27.49,"quality":5.88,"qualityChange":0.03},{"productId":158,"product":"Сковорода","productName":"pan","volume":221840000,"volumeChange":0.055,"amount":46424,"amountChange":0.051,"priceLevel":24.34,"sellers":26,"sellersChange":1,"divisions":107,"divisionsChange":5,"competition":3,"price":4776,"priceChange":36.25,"quality":6.26,"qualityChange":0.06},{"productId":106,"product":"Стиральный порошок","productName":"soappowder","volume":257820000,"volumeChange":0.027999999999999997,"amount":78631,"amountChange":0.025,"priceLevel":21.23,"sellers":37,"sellersChange":0,"divisions":217,"divisionsChange":0,"competition":6,"price":3278,"priceChange":7.46,"quality":5.47,"qualityChange":0.05},{"productId":134,"product":"Стол","productName":"table","volume":227940000,"volumeChange":0.065,"amount":8726,"amountChange":0.062,"priceLevel":44.65,"sellers":26,"sellersChange":2,"divisions":115,"divisionsChange":11,"competition":4,"price":26154,"priceChange":219.49,"quality":5.76,"qualityChange":0.08},{"productId":445,"product":"Стремянка","productName":"ladder","volume":261390000,"volumeChange":0.047,"amount":13348,"amountChange":0.031,"priceLevel":45.52,"sellers":36,"sellersChange":-1,"divisions":130,"divisionsChange":-1,"competition":3,"price":19551,"priceChange":214.14,"quality":6.02,"qualityChange":0.09},{"productId":420,"product":"Стул","productName":"stool","volume":215790000,"volumeChange":0.057999999999999996,"amount":24456,"amountChange":0.061,"priceLevel":57.48,"sellers":24,"sellersChange":0,"divisions":100,"divisionsChange":-1,"competition":2,"price":8804,"priceChange":-62.5,"quality":5.79,"qualityChange":0.02},{"productId":113,"product":"Утюг","productName":"iron","volume":261170000.00000003,"volumeChange":0.04,"amount":33763,"amountChange":0.036000000000000004,"priceLevel":23.96,"sellers":38,"sellersChange":-1,"divisions":132,"divisionsChange":-3,"competition":3,"price":7704,"priceChange":-15.18,"quality":5.97,"qualityChange":0.08},{"productId":320,"product":"Чайник","productName":"teapot","volume":244970000,"volumeChange":0.04,"amount":42807,"amountChange":0.031,"priceLevel":54.51,"sellers":32,"sellersChange":-1,"divisions":130,"divisionsChange":-2,"competition":3,"price":5759,"priceChange":81.57,"quality":5.78,"qualityChange":0.04},{"productId":133,"product":"Шкаф","productName":"wardrobe","volume":261420000.00000003,"volumeChange":0.043,"amount":2062,"amountChange":0.042,"priceLevel":36.42,"sellers":39,"sellersChange":0,"divisions":184,"divisionsChange":-13,"competition":3,"price":127148,"priceChange":-77.42,"quality":5.63,"qualityChange":0}]},{"groupId":3,"group":"Одежда","groupName":"clothes","turnover":9680000000,"turnoverChange":0.069,"share":0.1527,"margin":1.5,"competition":3,"priceLevel":44.51,"products":[{"productId":207,"product":"Блузка","productName":"blouse","volume":435350000,"volumeChange":0.07,"amount":88243,"amountChange":0.067,"priceLevel":46.1,"sellers":36,"sellersChange":-2,"divisions":188,"divisionsChange":-3,"competition":3,"price":4937,"priceChange":20.39,"quality":5.16,"qualityChange":0.04},{"productId":137,"product":"Ботинки","productName":"manshoes","volume":356490000,"volumeChange":0.07200000000000001,"amount":26504,"amountChange":0.067,"priceLevel":49.91,"sellers":27,"sellersChange":-1,"divisions":118,"divisionsChange":-2,"competition":2,"price":13505,"priceChange":101.18,"quality":5.61,"qualityChange":-0.01},{"productId":462,"product":"Галстук","productName":"tie","volume":374060000,"volumeChange":0.131,"amount":81882,"amountChange":0.131,"priceLevel":34.68,"sellers":30,"sellersChange":0,"divisions":124,"divisionsChange":4,"competition":2,"price":4577,"priceChange":-2.88,"quality":5.1,"qualityChange":-0.01},{"productId":396,"product":"Джинсы","productName":"jeans","volume":298400000,"volumeChange":0.047,"amount":24684,"amountChange":0.05,"priceLevel":32,"sellers":33,"sellersChange":-2,"divisions":105,"divisionsChange":-3,"competition":2,"price":12036,"priceChange":-56.06,"quality":5.2,"qualityChange":0.02},{"productId":460,"product":"Дубленка","productName":"sheepskin","volume":500180000,"volumeChange":0.096,"amount":6534,"amountChange":0.099,"priceLevel":83.83,"sellers":41,"sellersChange":-2,"divisions":227,"divisionsChange":-10,"competition":4,"price":76534,"priceChange":-224.02,"quality":5.18,"qualityChange":0},{"productId":204,"product":"Костюм","productName":"suit","volume":267690000,"volumeChange":0.1,"amount":16305,"amountChange":0.113,"priceLevel":21.74,"sellers":32,"sellersChange":-2,"divisions":97,"divisionsChange":2,"competition":2,"price":16297,"priceChange":-194.11,"quality":5.15,"qualityChange":0.07},{"productId":203,"product":"Куртка","productName":"jacket","volume":364620000,"volumeChange":0.064,"amount":23152,"amountChange":0.069,"priceLevel":11.65,"sellers":32,"sellersChange":-1,"divisions":156,"divisionsChange":-6,"competition":3,"price":15748,"priceChange":-56,"quality":5.15,"qualityChange":0},{"productId":326,"product":"Носки","productName":"socks","volume":406870000,"volumeChange":0.049,"amount":1902287,"amountChange":0.047,"priceLevel":56.72,"sellers":34,"sellersChange":-2,"divisions":167,"divisionsChange":-4,"competition":4,"price":214,"priceChange":0.23,"quality":5.14,"qualityChange":0.01},{"productId":206,"product":"Пальто","productName":"mancoat","volume":338000000,"volumeChange":0.048,"amount":12533,"amountChange":0.064,"priceLevel":69.07,"sellers":28,"sellersChange":-1,"divisions":124,"divisionsChange":-2,"competition":2,"price":26736,"priceChange":-560.4,"quality":5.06,"qualityChange":-0.05},{"productId":149,"product":"Перчатки","productName":"gloves","volume":420330000,"volumeChange":0.057999999999999996,"amount":191093,"amountChange":0.06,"priceLevel":33.39,"sellers":39,"sellersChange":1,"divisions":175,"divisionsChange":13,"competition":4,"price":2184,"priceChange":-10.61,"quality":5.07,"qualityChange":-0.04},{"productId":208,"product":"Платье","productName":"dress","volume":466380000,"volumeChange":0.076,"amount":32318,"amountChange":0.07400000000000001,"priceLevel":62.42,"sellers":34,"sellersChange":-2,"divisions":179,"divisionsChange":-3,"competition":3,"price":14486,"priceChange":117.31,"quality":5.17,"qualityChange":0.04},{"productId":435,"product":"Пуховик","productName":"downjacket","volume":436370000,"volumeChange":0.099,"amount":12401,"amountChange":0.111,"priceLevel":53.11,"sellers":40,"sellersChange":2,"divisions":227,"divisionsChange":9,"competition":5,"price":34997,"priceChange":-427.62,"quality":5.18,"qualityChange":0.05},{"productId":148,"product":"Ремень","productName":"belt","volume":372250000,"volumeChange":0.055999999999999994,"amount":92476,"amountChange":0.059000000000000004,"priceLevel":31.21,"sellers":30,"sellersChange":0,"divisions":122,"divisionsChange":1,"competition":2,"price":4020,"priceChange":-13.29,"quality":5.24,"qualityChange":-0.02},{"productId":205,"product":"Рубашка","productName":"shirt","volume":269730000,"volumeChange":0.028999999999999998,"amount":58835,"amountChange":0.036000000000000004,"priceLevel":40.19,"sellers":33,"sellersChange":-1,"divisions":97,"divisionsChange":-1,"competition":2,"price":4589,"priceChange":-8.5,"quality":4.92,"qualityChange":0.01},{"productId":458,"product":"Сапоги","productName":"boots","volume":394840000,"volumeChange":0.032,"amount":12069,"amountChange":0.026000000000000002,"priceLevel":32.62,"sellers":34,"sellersChange":-2,"divisions":157,"divisionsChange":-4,"competition":3,"price":32594,"priceChange":-54.07,"quality":5.58,"qualityChange":-0.05},{"productId":461,"product":"Свитер","productName":"sweater","volume":358090000,"volumeChange":0.036000000000000004,"amount":28881,"amountChange":0.02,"priceLevel":29.81,"sellers":29,"sellersChange":-3,"divisions":166,"divisionsChange":-11,"competition":4,"price":12435,"priceChange":119.27,"quality":5.55,"qualityChange":0.04},{"productId":459,"product":"Сланцы","productName":"slates","volume":444140000,"volumeChange":0.077,"amount":218017,"amountChange":0.081,"priceLevel":46.81,"sellers":31,"sellersChange":-3,"divisions":173,"divisionsChange":-4,"competition":3,"price":2032,"priceChange":-9.7,"quality":5.51,"qualityChange":0.02},{"productId":436,"product":"Толстовка","productName":"sweatshirt","volume":429590000,"volumeChange":0.105,"amount":32076,"amountChange":0.10099999999999999,"priceLevel":48.08,"sellers":32,"sellersChange":0,"divisions":135,"divisionsChange":0,"competition":2,"price":13396,"priceChange":103.82,"quality":5.29,"qualityChange":0.05},{"productId":138,"product":"Туфли","productName":"womanshoes","volume":370980000,"volumeChange":0.064,"amount":35267,"amountChange":0.06,"priceLevel":27.16,"sellers":36,"sellersChange":0,"divisions":181,"divisionsChange":0,"competition":3,"price":10575,"priceChange":118.23,"quality":5.54,"qualityChange":0.08},{"productId":395,"product":"Футболка","productName":"tshirt","volume":408440000,"volumeChange":0.092,"amount":132603,"amountChange":0.1,"priceLevel":36.94,"sellers":32,"sellersChange":-1,"divisions":164,"divisionsChange":-2,"competition":3,"price":3078,"priceChange":-12.24,"quality":5.21,"qualityChange":-0.02},{"productId":397,"product":"Шапка","productName":"cap","volume":285930000,"volumeChange":0.09,"amount":94168,"amountChange":0.084,"priceLevel":33.07,"sellers":35,"sellersChange":1,"divisions":150,"divisionsChange":6,"competition":4,"price":3026,"priceChange":5.18,"quality":5.14,"qualityChange":0.03},{"productId":439,"product":"Шарф","productName":"scarf","volume":397680000,"volumeChange":0.038,"amount":188850,"amountChange":0.036000000000000004,"priceLevel":58.61,"sellers":39,"sellersChange":0,"divisions":214,"divisionsChange":0,"competition":5,"price":2102,"priceChange":0.21,"quality":5.09,"qualityChange":0.02},{"productId":434,"product":"Шорты","productName":"shorts","volume":380020000,"volumeChange":0.04,"amount":68607,"amountChange":0.034,"priceLevel":55.98,"sellers":31,"sellersChange":-2,"divisions":111,"divisionsChange":-16,"competition":1,"price":5572,"priceChange":57.3,"quality":5.31,"qualityChange":-0.02},{"productId":210,"product":"Шуба","productName":"furcoat","volume":481960000,"volumeChange":0.098,"amount":4292,"amountChange":0.10099999999999999,"priceLevel":50.64,"sellers":46,"sellersChange":0,"divisions":266,"divisionsChange":-9,"competition":6,"price":112684,"priceChange":-20.07,"quality":5.2,"qualityChange":0.02},{"productId":433,"product":"Юбка","productName":"skirt","volume":422950000,"volumeChange":0.051,"amount":47702,"amountChange":0.052000000000000005,"priceLevel":34.77,"sellers":36,"sellersChange":-1,"divisions":174,"divisionsChange":-4,"competition":3,"price":8811,"priceChange":-48.25,"quality":5.22,"qualityChange":-0.04}]},{"groupId":12,"group":"Фармацевтика","groupName":"pharma","turnover":3680000000,"turnoverChange":0.079,"share":0.057999999999999996,"margin":1.73,"competition":3,"priceLevel":54.83,"products":[{"productId":344,"product":"Антибиотики","productName":"antibiotics","volume":248630000,"volumeChange":0.08199999999999999,"amount":62104,"amountChange":0.07,"priceLevel":41.99,"sellers":37,"sellersChange":0,"divisions":224,"divisionsChange":0,"competition":4,"price":4010,"priceChange":40.71,"quality":5.19,"qualityChange":0.03},{"productId":416,"product":"Антисептик","productName":"antiseptic","volume":239750000,"volumeChange":0.087,"amount":256679,"amountChange":0.092,"priceLevel":49.14,"sellers":32,"sellersChange":0,"divisions":207,"divisionsChange":2,"competition":3,"price":937,"priceChange":-1.61,"quality":5.2,"qualityChange":-0.03},{"productId":334,"product":"БАД","productName":"supplements","volume":223350000,"volumeChange":0.057999999999999996,"amount":37492,"amountChange":0.040999999999999995,"priceLevel":57.28,"sellers":28,"sellersChange":-5,"divisions":169,"divisionsChange":-13,"competition":3,"price":5981,"priceChange":87.9,"quality":5.13,"qualityChange":0.1},{"productId":343,"product":"Вакцина","productName":"vaccine","volume":241490000,"volumeChange":0.07200000000000001,"amount":65980,"amountChange":0.066,"priceLevel":36.96,"sellers":38,"sellersChange":1,"divisions":224,"divisionsChange":24,"competition":4,"price":3664,"priceChange":18.96,"quality":5.29,"qualityChange":-0.02},{"productId":333,"product":"Витамины","productName":"vitamins","volume":203790000,"volumeChange":0.044000000000000004,"amount":163207,"amountChange":0.031,"priceLevel":10.01,"sellers":32,"sellersChange":0,"divisions":197,"divisionsChange":0,"competition":3,"price":1253,"priceChange":15.26,"quality":5.31,"qualityChange":0.07},{"productId":337,"product":"Контрацептивы","productName":"contraceptives","volume":256430000,"volumeChange":0.083,"amount":270068,"amountChange":0.081,"priceLevel":58.31,"sellers":34,"sellersChange":0,"divisions":198,"divisionsChange":0,"competition":3,"price":951,"priceChange":3.29,"quality":5.39,"qualityChange":0.05},{"productId":384,"product":"Лечебный крем","productName":"healingcream","volume":253300000,"volumeChange":0.091,"amount":38727,"amountChange":0.086,"priceLevel":84.22,"sellers":32,"sellersChange":-1,"divisions":191,"divisionsChange":-6,"competition":3,"price":6570,"priceChange":41.74,"quality":5.19,"qualityChange":-0.02},{"productId":455,"product":"Линзы","productName":"lenses","volume":261149999.99999997,"volumeChange":0.086,"amount":113795,"amountChange":0.06,"priceLevel":97.88,"sellers":35,"sellersChange":-2,"divisions":182,"divisionsChange":0,"competition":2,"price":2327,"priceChange":81.28,"quality":5.41,"qualityChange":0.08},{"productId":339,"product":"Мед техника","productName":"medtechnic","volume":271790000,"volumeChange":0.11,"amount":3650,"amountChange":0.1,"priceLevel":75.1,"sellers":38,"sellersChange":0,"divisions":208,"divisionsChange":0,"competition":3,"price":74047,"priceChange":-399.58,"quality":5.92,"qualityChange":0.11},{"productId":336,"product":"Настойка","productName":"tincture","volume":261459999.99999997,"volumeChange":0.094,"amount":69976,"amountChange":0.091,"priceLevel":88.44,"sellers":40,"sellersChange":2,"divisions":225,"divisionsChange":10,"competition":2,"price":3743,"priceChange":5.14,"quality":5.19,"qualityChange":-0.01},{"productId":340,"product":"Ортопедические изделия","productName":"orthopedic","volume":253860000,"volumeChange":0.08900000000000001,"amount":28004,"amountChange":0.078,"priceLevel":70.51,"sellers":36,"sellersChange":0,"divisions":202,"divisionsChange":3,"competition":3,"price":9113,"priceChange":116.18,"quality":5.46,"qualityChange":0.01},{"productId":338,"product":"Перевязочные средства","productName":"bandage","volume":256860000,"volumeChange":0.098,"amount":356802,"amountChange":0.10099999999999999,"priceLevel":43.97,"sellers":36,"sellersChange":-1,"divisions":216,"divisionsChange":3,"competition":4,"price":720,"priceChange":-4.09,"quality":5.52,"qualityChange":0.05},{"productId":342,"product":"Противопростудные","productName":"cough","volume":225850000,"volumeChange":0.063,"amount":62969,"amountChange":0.06,"priceLevel":9.79,"sellers":32,"sellersChange":0,"divisions":200,"divisionsChange":1,"competition":3,"price":3585,"priceChange":-16.38,"quality":5.31,"qualityChange":0.02},{"productId":341,"product":"Рецептурные препараты","productName":"prescription","volume":245140000,"volumeChange":0.049,"amount":177671,"amountChange":0.043,"priceLevel":38.59,"sellers":38,"sellersChange":-1,"divisions":225,"divisionsChange":-18,"competition":3,"price":1378,"priceChange":2.8,"quality":5.04,"qualityChange":0.1},{"productId":418,"product":"Травяной сбор","productName":"herbal","volume":232160000,"volumeChange":0.066,"amount":238571,"amountChange":0.077,"priceLevel":39.86,"sellers":31,"sellersChange":-1,"divisions":197,"divisionsChange":-2,"competition":3,"price":982,"priceChange":3.99,"quality":5.24,"qualityChange":-0.03}]},{"groupId":4,"group":"Электроника","groupName":"electronics","turnover":9630000000,"turnoverChange":0.083,"share":0.152,"margin":1.68,"competition":5,"priceLevel":56.61,"products":[{"productId":117,"product":"Аудиотехника","productName":"audio","volume":547240000,"volumeChange":0.106,"amount":11807,"amountChange":0.096,"priceLevel":82.93,"sellers":54,"sellersChange":1,"divisions":357,"divisionsChange":4,"competition":5,"price":46500,"priceChange":632.95,"quality":5.92,"qualityChange":0.13},{"productId":409,"product":"Варочная панель","productName":"hob","volume":480090000,"volumeChange":0.077,"amount":19298,"amountChange":0.081,"priceLevel":39.04,"sellers":42,"sellersChange":0,"divisions":217,"divisionsChange":0,"competition":4,"price":24854,"priceChange":-4.09,"quality":5.8,"qualityChange":0.03},{"productId":410,"product":"Вытяжка","productName":"hood","volume":541860000,"volumeChange":0.146,"amount":23320,"amountChange":0.142,"priceLevel":82.52,"sellers":41,"sellersChange":0,"divisions":205,"divisionsChange":1,"competition":3,"price":23145,"priceChange":-26.41,"quality":5.71,"qualityChange":0.07},{"productId":318,"product":"Игровая приставка","productName":"xbox","volume":464690000,"volumeChange":0.061,"amount":10036,"amountChange":0.067,"priceLevel":63.87,"sellers":52,"sellersChange":-2,"divisions":263,"divisionsChange":-16,"competition":6,"price":46457,"priceChange":-342.07,"quality":5.93,"qualityChange":-0.09},{"productId":381,"product":"Кухонный комбайн","productName":"foodprocessor","volume":517900000,"volumeChange":0.122,"amount":7535,"amountChange":0.11900000000000001,"priceLevel":44.09,"sellers":39,"sellersChange":0,"divisions":199,"divisionsChange":0,"competition":5,"price":69046,"priceChange":223.55,"quality":5.66,"qualityChange":-0.02},{"productId":316,"product":"Микроволновка","productName":"microwave","volume":443880000,"volumeChange":0.102,"amount":6539,"amountChange":0.092,"priceLevel":38.03,"sellers":42,"sellersChange":1,"divisions":202,"divisionsChange":3,"competition":3,"price":68251,"priceChange":886.77,"quality":5.73,"qualityChange":0.04},{"productId":125,"product":"Настольный компьютер","productName":"computer","volume":561950000,"volumeChange":0.129,"amount":4036,"amountChange":0.129,"priceLevel":100,"sellers":50,"sellersChange":1,"divisions":358,"divisionsChange":5,"competition":6,"price":139385,"priceChange":121.16,"quality":5.44,"qualityChange":-0.01},{"productId":371,"product":"Наушники","productName":"headphones","volume":419910000,"volumeChange":0.040999999999999995,"amount":43622,"amountChange":0.04,"priceLevel":42.94,"sellers":54,"sellersChange":0,"divisions":280,"divisionsChange":1,"competition":6,"price":9664,"priceChange":32.03,"quality":5.82,"qualityChange":0.02},{"productId":126,"product":"Ноутбук","productName":"notebook","volume":527730000,"volumeChange":0.195,"amount":3100,"amountChange":0.191,"priceLevel":64.45,"sellers":52,"sellersChange":-2,"divisions":232,"divisionsChange":-16,"competition":5,"price":170707,"priceChange":828.78,"quality":6.06,"qualityChange":0.03},{"productId":317,"product":"Планшет","productName":"tablet","volume":495010000,"volumeChange":0.027999999999999997,"amount":10343,"amountChange":0.003,"priceLevel":81.44,"sellers":47,"sellersChange":-4,"divisions":285,"divisionsChange":-73,"competition":4,"price":48408,"priceChange":1355.52,"quality":5.97,"qualityChange":0.1},{"productId":112,"product":"Посудомоечная машина","productName":"dishwasher","volume":486670000,"volumeChange":0.13699999999999998,"amount":3653,"amountChange":0.139,"priceLevel":34.98,"sellers":38,"sellersChange":-1,"divisions":194,"divisionsChange":-2,"competition":4,"price":133547,"priceChange":27.84,"quality":5.58,"qualityChange":-0.03},{"productId":128,"product":"Принтер","productName":"printer","volume":504000000,"volumeChange":0.085,"amount":5694,"amountChange":0.076,"priceLevel":50.47,"sellers":54,"sellersChange":-1,"divisions":341,"divisionsChange":-5,"competition":6,"price":88861,"priceChange":812.04,"quality":6.25,"qualityChange":0.06},{"productId":372,"product":"Смарт часы","productName":"smartwatch","volume":447390000,"volumeChange":0.006,"amount":28148,"amountChange":0.006,"priceLevel":45.86,"sellers":52,"sellersChange":-2,"divisions":240,"divisionsChange":-18,"competition":5,"price":15972,"priceChange":-92.35,"quality":5.88,"qualityChange":-0.06},{"productId":129,"product":"Смартфон","productName":"smartphone","volume":435850000,"volumeChange":0.046,"amount":10620,"amountChange":0.034,"priceLevel":59.04,"sellers":54,"sellersChange":1,"divisions":243,"divisionsChange":2,"competition":5,"price":40991,"priceChange":204.6,"quality":6.29,"qualityChange":0.03},{"productId":456,"product":"Спутниковое оборудование","productName":"satellite","volume":352790000,"volumeChange":-0.134,"amount":10195,"amountChange":-0.134,"priceLevel":56.76,"sellers":30,"sellersChange":-5,"divisions":126,"divisionsChange":-38,"competition":2,"price":34387,"priceChange":-350.48,"quality":5.5,"qualityChange":-0.04},{"productId":111,"product":"Стиральная машина","productName":"washer","volume":516409999.99999994,"volumeChange":0.11699999999999999,"amount":5120,"amountChange":0.107,"priceLevel":38.16,"sellers":40,"sellersChange":-1,"divisions":214,"divisionsChange":-2,"competition":4,"price":101229,"priceChange":1044.34,"quality":5.67,"qualityChange":0.03},{"productId":115,"product":"Телевизор","productName":"tv","volume":443630000,"volumeChange":0.07400000000000001,"amount":1939,"amountChange":0.078,"priceLevel":53.97,"sellers":45,"sellersChange":-1,"divisions":199,"divisionsChange":-4,"competition":3,"price":228881,"priceChange":-608.2,"quality":5.51,"qualityChange":-0.07},{"productId":457,"product":"Умная колонка","productName":"speaker","volume":470000000,"volumeChange":0.11800000000000001,"amount":20082,"amountChange":0.11800000000000001,"priceLevel":59.47,"sellers":46,"sellersChange":-1,"divisions":210,"divisionsChange":-4,"competition":3,"price":23404,"priceChange":-6.14,"quality":5.75,"qualityChange":0},{"productId":151,"product":"Фотоаппарат","productName":"photo","volume":470860000,"volumeChange":0.08800000000000001,"amount":6695,"amountChange":0.083,"priceLevel":45.28,"sellers":51,"sellersChange":0,"divisions":263,"divisionsChange":1,"competition":5,"price":70305,"priceChange":267.37,"quality":5.86,"qualityChange":0.03},{"productId":110,"product":"Холодильник","productName":"refrigirator","volume":507120000,"volumeChange":0.092,"amount":3812,"amountChange":0.09,"priceLevel":33.55,"sellers":39,"sellersChange":-1,"divisions":213,"divisionsChange":-2,"competition":4,"price":133404,"priceChange":327.66,"quality":5.61,"qualityChange":0.02}]},{"groupId":7,"group":"Стройматериалы","groupName":"constructive","turnover":2930000000,"turnoverChange":0.057999999999999996,"share":0.0463,"margin":1.66,"competition":5,"priceLevel":37.09,"products":[{"productId":348,"product":"Герметик","productName":"glue","volume":142790000,"volumeChange":0.054000000000000006,"amount":284951,"amountChange":0.048,"priceLevel":20.81,"sellers":24,"sellersChange":-1,"divisions":109,"divisionsChange":-1,"competition":3,"price":503,"priceChange":6.54,"quality":5.92,"qualityChange":0.04},{"productId":323,"product":"Дверь","productName":"door","volume":155220000,"volumeChange":0.043,"amount":7903,"amountChange":0.055,"priceLevel":57.69,"sellers":27,"sellersChange":-1,"divisions":119,"divisionsChange":-2,"competition":4,"price":19904,"priceChange":35.21,"quality":5.62,"qualityChange":0.02},{"productId":449,"product":"Зеркало","productName":"mirror","volume":153010000,"volumeChange":0.05,"amount":11681,"amountChange":0.038,"priceLevel":52.2,"sellers":23,"sellersChange":-1,"divisions":106,"divisionsChange":-4,"competition":5,"price":13113,"priceChange":121.19,"quality":6.2,"qualityChange":0.01},{"productId":244,"product":"Инструменты","productName":"tools","volume":142240000,"volumeChange":0.055999999999999994,"amount":2385,"amountChange":0.057,"priceLevel":70.6,"sellers":23,"sellersChange":1,"divisions":102,"divisionsChange":1,"competition":4,"price":59750,"priceChange":75.45,"quality":5.8,"qualityChange":0.03},{"productId":324,"product":"Керамическая плитка","productName":"tile","volume":151980000,"volumeChange":0.052000000000000005,"amount":10839,"amountChange":0.047,"priceLevel":50.37,"sellers":24,"sellersChange":0,"divisions":110,"divisionsChange":1,"competition":5,"price":14008,"priceChange":60.98,"quality":5.11,"qualityChange":0.02},{"productId":446,"product":"Ковер","productName":"carpet","volume":144040000,"volumeChange":0.07,"amount":7302,"amountChange":0.092,"priceLevel":23.39,"sellers":24,"sellersChange":0,"divisions":104,"divisionsChange":1,"competition":4,"price":19800,"priceChange":-158.75,"quality":5.32,"qualityChange":-0.01},{"productId":374,"product":"Кондиционер","productName":"conditioning","volume":138580000,"volumeChange":0.057,"amount":956,"amountChange":0.048,"priceLevel":41.12,"sellers":19,"sellersChange":0,"divisions":97,"divisionsChange":0,"competition":3,"price":145449,"priceChange":1016.73,"quality":5.65,"qualityChange":0.02},{"productId":32,"product":"Краска","productName":"paint","volume":141650000,"volumeChange":0.048,"amount":5266,"amountChange":0.045,"priceLevel":49.98,"sellers":21,"sellersChange":1,"divisions":104,"divisionsChange":1,"competition":3,"price":26923,"priceChange":73.94,"quality":6.2,"qualityChange":0.01},{"productId":419,"product":"Крепеж","productName":"fasteners","volume":143070000,"volumeChange":0.08,"amount":27043,"amountChange":0.069,"priceLevel":35.59,"sellers":27,"sellersChange":1,"divisions":107,"divisionsChange":8,"competition":3,"price":5285,"priceChange":32.47,"quality":6.12,"qualityChange":0.03},{"productId":240,"product":"Напольные покрытия","productName":"floor","volume":157530000,"volumeChange":0.07200000000000001,"amount":25298,"amountChange":0.07400000000000001,"priceLevel":60.8,"sellers":28,"sellersChange":-1,"divisions":125,"divisionsChange":2,"competition":4,"price":6236,"priceChange":12.53,"quality":5.72,"qualityChange":0},{"productId":407,"product":"Обогреватель","productName":"heater","volume":148110000,"volumeChange":0.065,"amount":2709,"amountChange":0.054000000000000006,"priceLevel":0.06,"sellers":24,"sellersChange":0,"divisions":109,"divisionsChange":0,"competition":5,"price":54895,"priceChange":610.45,"quality":5.61,"qualityChange":0},{"productId":239,"product":"Обои","productName":"wallpaper","volume":139390000,"volumeChange":0.048,"amount":16924,"amountChange":0.044000000000000004,"priceLevel":7.39,"sellers":29,"sellersChange":0,"divisions":117,"divisionsChange":0,"competition":3,"price":8221,"priceChange":9.81,"quality":5.87,"qualityChange":0.15},{"productId":249,"product":"Окна","productName":"window","volume":155860000,"volumeChange":0.055,"amount":2454,"amountChange":0.053,"priceLevel":35.02,"sellers":29,"sellersChange":0,"divisions":130,"divisionsChange":0,"competition":4,"price":63506,"priceChange":105.4,"quality":5.85,"qualityChange":0.04},{"productId":370,"product":"Провода","productName":"wires","volume":141610000,"volumeChange":0.046,"amount":17086,"amountChange":0.043,"priceLevel":8.76,"sellers":21,"sellersChange":0,"divisions":100,"divisionsChange":0,"competition":3,"price":8285,"priceChange":10.48,"quality":5.87,"qualityChange":0.03},{"productId":242,"product":"Сантехника","productName":"sanitary","volume":154010000,"volumeChange":0.052000000000000005,"amount":8456,"amountChange":0.048,"priceLevel":51.58,"sellers":23,"sellersChange":-1,"divisions":102,"divisionsChange":-10,"competition":5,"price":18165,"priceChange":116.87,"quality":5.57,"qualityChange":0.09},{"productId":241,"product":"Светильник","productName":"lamp","volume":154810000,"volumeChange":0.059000000000000004,"amount":9397,"amountChange":0.054000000000000006,"priceLevel":67.02,"sellers":26,"sellersChange":0,"divisions":111,"divisionsChange":1,"competition":5,"price":16500,"priceChange":85.2,"quality":5.62,"qualityChange":0.02},{"productId":411,"product":"Трубы","productName":"pipes","volume":153560000,"volumeChange":0.047,"amount":1651,"amountChange":0.038,"priceLevel":33.94,"sellers":29,"sellersChange":0,"divisions":119,"divisionsChange":0,"competition":4,"price":93612,"priceChange":758.2,"quality":5.47,"qualityChange":0.02},{"productId":447,"product":"Фурнитура","productName":"fittings","volume":137310000,"volumeChange":0.028999999999999998,"amount":33756,"amountChange":0.047,"priceLevel":0,"sellers":21,"sellersChange":-3,"divisions":100,"divisionsChange":-12,"competition":3,"price":4031,"priceChange":-76.33,"quality":6.2,"qualityChange":0},{"productId":412,"product":"Шторы","productName":"curtains","volume":135280000,"volumeChange":0.07,"amount":1654,"amountChange":0.057999999999999996,"priceLevel":34.01,"sellers":22,"sellersChange":1,"divisions":98,"divisionsChange":1,"competition":4,"price":81949,"priceChange":584.94,"quality":5.53,"qualityChange":0.01},{"productId":448,"product":"Штукатурка","productName":"plaster","volume":143600000,"volumeChange":0.12,"amount":17532,"amountChange":0.09699999999999999,"priceLevel":31.32,"sellers":24,"sellersChange":0,"divisions":104,"divisionsChange":7,"competition":4,"price":8171,"priceChange":88.89,"quality":5.93,"qualityChange":0}]},{"groupId":13,"group":"Спорттовары","groupName":"sport","turnover":3760000000,"turnoverChange":0.105,"share":0.0593,"margin":1.62,"competition":5,"priceLevel":37.53,"products":[{"productId":120,"product":"Велосипед","productName":"bicycle","volume":144040000,"volumeChange":0.10400000000000001,"amount":2483,"amountChange":0.10300000000000001,"priceLevel":23.62,"sellers":19,"sellersChange":0,"divisions":93,"divisionsChange":0,"competition":4,"price":58028,"priceChange":66.98,"quality":6.06,"qualityChange":0},{"productId":350,"product":"Гантели","productName":"dumbbells","volume":165060000,"volumeChange":0.12,"amount":42628,"amountChange":0.11900000000000001,"priceLevel":41.84,"sellers":23,"sellersChange":0,"divisions":102,"divisionsChange":-3,"competition":6,"price":3872,"priceChange":0.48,"quality":5.7,"qualityChange":0},{"productId":414,"product":"Коврик","productName":"rug","volume":140880000,"volumeChange":0.094,"amount":57619,"amountChange":0.096,"priceLevel":19.79,"sellers":19,"sellersChange":0,"divisions":94,"divisionsChange":0,"competition":4,"price":2425,"priceChange":-23.09,"quality":5.96,"qualityChange":0.16},{"productId":351,"product":"Компрессионная одежда","productName":"compression","volume":135040000,"volumeChange":0.09699999999999999,"amount":11608,"amountChange":0.098,"priceLevel":19.06,"sellers":19,"sellersChange":0,"divisions":84,"divisionsChange":0,"competition":4,"price":11628,"priceChange":-6.45,"quality":6.08,"qualityChange":0.01},{"productId":361,"product":"Коньки","productName":"skates","volume":162290000,"volumeChange":0.11599999999999999,"amount":11530,"amountChange":0.113,"priceLevel":44.25,"sellers":21,"sellersChange":0,"divisions":99,"divisionsChange":0,"competition":6,"price":14082,"priceChange":21.12,"quality":6.06,"qualityChange":0.05},{"productId":140,"product":"Кросовки","productName":"sportshoes","volume":115050000,"volumeChange":0.076,"amount":16914,"amountChange":0.059000000000000004,"priceLevel":6.75,"sellers":19,"sellersChange":1,"divisions":75,"divisionsChange":1,"competition":3,"price":6840,"priceChange":122.17,"quality":5.46,"qualityChange":0.06},{"productId":362,"product":"Лыжи","productName":"skiing","volume":160990000,"volumeChange":0.11699999999999999,"amount":5863,"amountChange":0.11800000000000001,"priceLevel":24.28,"sellers":21,"sellersChange":0,"divisions":100,"divisionsChange":0,"competition":5,"price":27449,"priceChange":-27.93,"quality":6.14,"qualityChange":0},{"productId":363,"product":"Мяч","productName":"ball","volume":134260000,"volumeChange":0.094,"amount":12821,"amountChange":0.09699999999999999,"priceLevel":18.27,"sellers":22,"sellersChange":1,"divisions":82,"divisionsChange":1,"competition":4,"price":10463,"priceChange":-20.5,"quality":5.92,"qualityChange":0.02},{"productId":357,"product":"Надувной матрас","productName":"mattress","volume":153720000,"volumeChange":0.10300000000000001,"amount":59845,"amountChange":0.10300000000000001,"priceLevel":63.25,"sellers":24,"sellersChange":1,"divisions":98,"divisionsChange":3,"competition":6,"price":2569,"priceChange":-0.47,"quality":5.96,"qualityChange":0},{"productId":352,"product":"Палатка","productName":"tent","volume":151670000,"volumeChange":0.099,"amount":4514,"amountChange":0.094,"priceLevel":41.87,"sellers":21,"sellersChange":-1,"divisions":94,"divisionsChange":-2,"competition":2,"price":33702,"priceChange":217.05,"quality":6.11,"qualityChange":0.02},{"productId":364,"product":"Ракетки","productName":"rackets","volume":150980000,"volumeChange":0.105,"amount":21681,"amountChange":0.111,"priceLevel":20.1,"sellers":24,"sellersChange":1,"divisions":94,"divisionsChange":1,"competition":5,"price":6945,"priceChange":-25.21,"quality":6.19,"qualityChange":0.06},{"productId":355,"product":"Резиновая лодка","productName":"rubberboat","volume":150380000,"volumeChange":0.10300000000000001,"amount":2458,"amountChange":0.109,"priceLevel":36.16,"sellers":21,"sellersChange":-1,"divisions":92,"divisionsChange":-1,"competition":4,"price":61122,"priceChange":-380.57,"quality":6,"qualityChange":-0.01},{"productId":359,"product":"Роликовые коньки","productName":"roller","volume":161970000,"volumeChange":0.114,"amount":11787,"amountChange":0.121,"priceLevel":31.93,"sellers":21,"sellersChange":1,"divisions":99,"divisionsChange":1,"competition":5,"price":13716,"priceChange":-45.88,"quality":6.12,"qualityChange":0.03},{"productId":354,"product":"Рюкзак","productName":"backpack","volume":152340000,"volumeChange":0.10400000000000001,"amount":7641,"amountChange":0.1,"priceLevel":32.8,"sellers":20,"sellersChange":0,"divisions":102,"divisionsChange":0,"competition":3,"price":19921,"priceChange":86.39,"quality":6.19,"qualityChange":0.04},{"productId":322,"product":"Солнечные очки","productName":"sunglasses","volume":126980000,"volumeChange":0.057999999999999996,"amount":30656,"amountChange":0.057999999999999996,"priceLevel":37.43,"sellers":19,"sellersChange":-1,"divisions":57,"divisionsChange":-5,"competition":3,"price":4137,"priceChange":-5.46,"quality":6.08,"qualityChange":0.01},{"productId":353,"product":"Спальный мешок","productName":"sleeping","volume":152670000,"volumeChange":0.105,"amount":7744,"amountChange":0.107,"priceLevel":31.79,"sellers":23,"sellersChange":1,"divisions":99,"divisionsChange":1,"competition":2,"price":19686,"priceChange":-68.13,"quality":6.29,"qualityChange":0.02},{"productId":145,"product":"Спортивная одежда","productName":"sportclothes","volume":145960000,"volumeChange":0.07400000000000001,"amount":12924,"amountChange":0.084,"priceLevel":40.31,"sellers":18,"sellersChange":-1,"divisions":95,"divisionsChange":-3,"competition":4,"price":11237,"priceChange":-112.12,"quality":5.14,"qualityChange":-0.03},{"productId":444,"product":"Спортивное питание","productName":"nutrition","volume":148930000,"volumeChange":0.115,"amount":51328,"amountChange":0.115,"priceLevel":27.94,"sellers":23,"sellersChange":0,"divisions":78,"divisionsChange":0,"competition":4,"price":2901,"priceChange":-0.78,"quality":5.72,"qualityChange":0},{"productId":415,"product":"Термос","productName":"thermos","volume":158180000,"volumeChange":0.115,"amount":48648,"amountChange":0.10800000000000001,"priceLevel":66.76,"sellers":23,"sellersChange":0,"divisions":105,"divisionsChange":0,"competition":5,"price":3264,"priceChange":35.45,"quality":5.66,"qualityChange":-0.02},{"productId":356,"product":"Топор","productName":"axe","volume":154900000,"volumeChange":0.106,"amount":41253,"amountChange":0.10300000000000001,"priceLevel":60.84,"sellers":23,"sellersChange":0,"divisions":104,"divisionsChange":0,"competition":4,"price":3755,"priceChange":3.61,"quality":5.78,"qualityChange":-0.03},{"productId":349,"product":"Тренажер","productName":"training","volume":155170000,"volumeChange":0.12,"amount":1326,"amountChange":0.11800000000000001,"priceLevel":24.66,"sellers":26,"sellersChange":2,"divisions":87,"divisionsChange":6,"competition":5,"price":117019,"priceChange":86.72,"quality":5.79,"qualityChange":0},{"productId":443,"product":"Удочка","productName":"rod","volume":152760000,"volumeChange":0.10400000000000001,"amount":17659,"amountChange":0.099,"priceLevel":65.39,"sellers":21,"sellersChange":0,"divisions":93,"divisionsChange":0,"competition":3,"price":8659,"priceChange":32.16,"quality":5.82,"qualityChange":0},{"productId":413,"product":"Фонарь","productName":"flashlight","volume":164380000,"volumeChange":0.106,"amount":24400,"amountChange":0.106,"priceLevel":58.8,"sellers":24,"sellersChange":1,"divisions":111,"divisionsChange":4,"competition":6,"price":6699,"priceChange":-24.4,"quality":5.92,"qualityChange":0.19},{"productId":406,"product":"Шлем","productName":"helmet","volume":157090000,"volumeChange":0.129,"amount":14665,"amountChange":0.138,"priceLevel":16.29,"sellers":20,"sellersChange":3,"divisions":94,"divisionsChange":7,"competition":5,"price":10714,"priceChange":-14.31,"quality":6.33,"qualityChange":-0.09},{"productId":360,"product":"Электросамокат","productName":"kickscooter","volume":163020000,"volumeChange":0.11699999999999999,"amount":3029,"amountChange":0.11599999999999999,"priceLevel":65.46,"sellers":26,"sellersChange":1,"divisions":94,"divisionsChange":1,"competition":6,"price":53884,"priceChange":93.07,"quality":5.86,"qualityChange":0.01}]},{"groupId":14,"group":"Детские товары","groupName":"childgoods","turnover":2820000000,"turnoverChange":0.069,"share":0.0444,"margin":1.6,"competition":5,"priceLevel":30.86,"products":[{"productId":432,"product":"Бутылочка","productName":"bottle","volume":183790000,"volumeChange":0.068,"amount":315637,"amountChange":0.07200000000000001,"priceLevel":14.77,"sellers":29,"sellersChange":-1,"divisions":181,"divisionsChange":5,"competition":5,"price":582,"priceChange":0.54,"quality":5.49,"qualityChange":0.01},{"productId":139,"product":"Детская обувь","productName":"childshoes","volume":190530000,"volumeChange":0.078,"amount":47086,"amountChange":0.08,"priceLevel":36.77,"sellers":35,"sellersChange":3,"divisions":175,"divisionsChange":9,"competition":5,"price":4044,"priceChange":-12.3,"quality":5.24,"qualityChange":-0.03},{"productId":144,"product":"Детская одежда","productName":"childclothes","volume":189700000,"volumeChange":0.07,"amount":48612,"amountChange":0.07,"priceLevel":30.91,"sellers":34,"sellersChange":1,"divisions":181,"divisionsChange":6,"competition":5,"price":3907,"priceChange":4.6,"quality":5.14,"qualityChange":0.05},{"productId":417,"product":"Детская смесь","productName":"babyfood","volume":182780000,"volumeChange":0.064,"amount":48172,"amountChange":0.066,"priceLevel":41.06,"sellers":30,"sellersChange":0,"divisions":163,"divisionsChange":0,"competition":4,"price":3797,"priceChange":-0.1,"quality":5.79,"qualityChange":-0.01},{"productId":425,"product":"Детские книги","productName":"books","volume":189390000,"volumeChange":0.08900000000000001,"amount":127810,"amountChange":0.10099999999999999,"priceLevel":21.45,"sellers":32,"sellersChange":1,"divisions":168,"divisionsChange":4,"competition":5,"price":1480,"priceChange":-8.66,"quality":6.04,"qualityChange":0.04},{"productId":426,"product":"Канцтовары","productName":"stationery","volume":194880000,"volumeChange":0.076,"amount":55711,"amountChange":0.079,"priceLevel":45.04,"sellers":35,"sellersChange":0,"divisions":171,"divisionsChange":1,"competition":6,"price":3495,"priceChange":4.61,"quality":5.82,"qualityChange":-0.05},{"productId":424,"product":"Коляска","productName":"stroller","volume":190670000,"volumeChange":0.075,"amount":3276,"amountChange":0.073,"priceLevel":23.28,"sellers":34,"sellersChange":-1,"divisions":176,"divisionsChange":-5,"competition":6,"price":58253,"priceChange":203.13,"quality":5.89,"qualityChange":0.02},{"productId":377,"product":"Конструктор","productName":"constructor","volume":183310000,"volumeChange":0.064,"amount":40888,"amountChange":0.06,"priceLevel":29.1,"sellers":27,"sellersChange":-1,"divisions":151,"divisionsChange":-2,"competition":5,"price":4476,"priceChange":10.79,"quality":6.14,"qualityChange":0.07},{"productId":427,"product":"Кукла","productName":"doll","volume":182160000,"volumeChange":0.064,"amount":10935,"amountChange":0.062,"priceLevel":57.21,"sellers":28,"sellersChange":-1,"divisions":152,"divisionsChange":-2,"competition":5,"price":16664,"priceChange":6.83,"quality":5.62,"qualityChange":0.04},{"productId":431,"product":"Мебель для детей","productName":"furniture","volume":195800000,"volumeChange":0.059000000000000004,"amount":5105,"amountChange":0.057,"priceLevel":45.97,"sellers":31,"sellersChange":-3,"divisions":174,"divisionsChange":-7,"competition":5,"price":38547,"priceChange":254.5,"quality":5.64,"qualityChange":0.02},{"productId":121,"product":"Мягкая игрушка","productName":"toys","volume":166230000,"volumeChange":0.012,"amount":61760,"amountChange":0.019,"priceLevel":18.74,"sellers":28,"sellersChange":-1,"divisions":160,"divisionsChange":-5,"competition":4,"price":2729,"priceChange":14.57,"quality":5.16,"qualityChange":0.01},{"productId":429,"product":"Настольные игры","productName":"boardgames","volume":193170000,"volumeChange":0.066,"amount":38451,"amountChange":0.07400000000000001,"priceLevel":17.83,"sellers":34,"sellersChange":-1,"divisions":179,"divisionsChange":-2,"competition":6,"price":5001,"priceChange":-51.93,"quality":5.97,"qualityChange":-0.02},{"productId":423,"product":"Подгузники","productName":"diapers","volume":189450000,"volumeChange":0.079,"amount":74086,"amountChange":0.07400000000000001,"priceLevel":19.63,"sellers":36,"sellersChange":-1,"divisions":183,"divisionsChange":-1,"competition":5,"price":2572,"priceChange":51.78,"quality":5.21,"qualityChange":0.04},{"productId":430,"product":"Тетрадь","productName":"exercisebook","volume":194650000,"volumeChange":0.08900000000000001,"amount":533258,"amountChange":0.08800000000000001,"priceLevel":45.29,"sellers":33,"sellersChange":0,"divisions":169,"divisionsChange":0,"competition":5,"price":364,"priceChange":0.34,"quality":5.97,"qualityChange":0.07},{"productId":428,"product":"Трансформер","productName":"transformer","volume":189400000,"volumeChange":0.07400000000000001,"amount":36848,"amountChange":0.075,"priceLevel":14.14,"sellers":35,"sellersChange":-1,"divisions":182,"divisionsChange":-2,"competition":5,"price":5152,"priceChange":18.71,"quality":5.99,"qualityChange":-0.02}]},{"groupId":6,"group":"Автомобильные товары","groupName":"automotive","turnover":5890000000,"turnoverChange":0.201,"share":0.0929,"margin":1.68,"competition":2,"priceLevel":59.86,"products":[{"productId":159,"product":"Автомобиль","productName":"car","volume":398450000,"volumeChange":0.20199999999999999,"amount":135,"amountChange":0.195,"priceLevel":36.9,"sellers":23,"sellersChange":0,"divisions":120,"divisionsChange":-4,"competition":3,"price":2949402,"priceChange":11289.5,"quality":6.24,"qualityChange":-0.01},{"productId":422,"product":"Аккумулятор","productName":"batterypack","volume":360290000,"volumeChange":0.134,"amount":13824,"amountChange":0.11199999999999999,"priceLevel":44.45,"sellers":22,"sellersChange":0,"divisions":128,"divisionsChange":1,"competition":2,"price":26205,"priceChange":584.07,"quality":6.19,"qualityChange":0.08},{"productId":398,"product":"Аксессуары","productName":"accessories","volume":407200000,"volumeChange":0.221,"amount":97095,"amountChange":0.213,"priceLevel":60.26,"sellers":22,"sellersChange":2,"divisions":134,"divisionsChange":8,"competition":2,"price":4189,"priceChange":12.15,"quality":6.17,"qualityChange":0.05},{"productId":399,"product":"Домкрат","productName":"jack","volume":495620000,"volumeChange":0.242,"amount":77096,"amountChange":0.24100000000000002,"priceLevel":85.92,"sellers":24,"sellersChange":0,"divisions":128,"divisionsChange":1,"competition":3,"price":6410,"priceChange":0.91,"quality":5.93,"qualityChange":0.06},{"productId":383,"product":"Квадроцикл","productName":"quadbike","volume":451870000,"volumeChange":0.213,"amount":351,"amountChange":0.20600000000000002,"priceLevel":50.94,"sellers":24,"sellersChange":0,"divisions":132,"divisionsChange":1,"competition":2,"price":1287606,"priceChange":5878.75,"quality":6.53,"qualityChange":0.03},{"productId":44,"product":"Комплектующие","productName":"parts","volume":313350000,"volumeChange":0.141,"amount":81794,"amountChange":0.142,"priceLevel":66.06,"sellers":20,"sellersChange":0,"divisions":96,"divisionsChange":0,"competition":1,"price":3826,"priceChange":-14.29,"quality":6.24,"qualityChange":0.07},{"productId":315,"product":"Компрессор","productName":"compressor","volume":453470000,"volumeChange":0.15,"amount":85614,"amountChange":0.163,"priceLevel":100,"sellers":22,"sellersChange":-2,"divisions":107,"divisionsChange":-20,"competition":2,"price":5312,"priceChange":-37.75,"quality":5.91,"qualityChange":-0.05},{"productId":376,"product":"Кузовные детали","productName":"bodyparts","volume":365010000,"volumeChange":0.18899999999999997,"amount":3033,"amountChange":0.171,"priceLevel":43.59,"sellers":23,"sellersChange":0,"divisions":124,"divisionsChange":2,"competition":2,"price":120974,"priceChange":1940.38,"quality":6.03,"qualityChange":0.02},{"productId":236,"product":"Машинное масло","productName":"machineoil","volume":382360000,"volumeChange":0.14800000000000002,"amount":33902,"amountChange":0.128,"priceLevel":25.19,"sellers":22,"sellersChange":0,"divisions":126,"divisionsChange":1,"competition":2,"price":11335,"priceChange":165.73,"quality":6.14,"qualityChange":0},{"productId":160,"product":"Мотоцикл","productName":"moto","volume":427690000,"volumeChange":0.27699999999999997,"amount":283,"amountChange":0.275,"priceLevel":80.91,"sellers":21,"sellersChange":0,"divisions":95,"divisionsChange":0,"competition":2,"price":1509859,"priceChange":2858.63,"quality":6.36,"qualityChange":0.01},{"productId":314,"product":"Омывающая жидкость","productName":"washerfluid","volume":291120000,"volumeChange":0.133,"amount":95878,"amountChange":0.134,"priceLevel":34.76,"sellers":20,"sellersChange":-1,"divisions":96,"divisionsChange":-1,"competition":2,"price":3041,"priceChange":0.41,"quality":6.62,"qualityChange":-0.02},{"productId":400,"product":"Сабвуфер","productName":"subwoofer","volume":451980000,"volumeChange":0.214,"amount":6518,"amountChange":0.201,"priceLevel":68.18,"sellers":23,"sellersChange":-1,"divisions":124,"divisionsChange":-1,"competition":3,"price":69528,"priceChange":927.21,"quality":6.06,"qualityChange":0.01},{"productId":346,"product":"Скутер","productName":"scooter","volume":310540000,"volumeChange":0.179,"amount":776,"amountChange":0.174,"priceLevel":26.17,"sellers":23,"sellersChange":0,"divisions":127,"divisionsChange":1,"competition":2,"price":401252,"priceChange":2000.63,"quality":6.56,"qualityChange":0},{"productId":161,"product":"Шины","productName":"tire","volume":378880000,"volumeChange":0.25,"amount":10386,"amountChange":0.248,"priceLevel":82.47,"sellers":21,"sellersChange":2,"divisions":100,"divisionsChange":3,"competition":1,"price":36437,"priceChange":38.95,"quality":6.12,"qualityChange":0.01},{"productId":378,"product":"Электромобиль","productName":"electriccar","volume":401150000,"volumeChange":0.294,"amount":86,"amountChange":0.284,"priceLevel":62.73,"sellers":21,"sellersChange":1,"divisions":100,"divisionsChange":1,"competition":1,"price":4668650,"priceChange":38896,"quality":6.15,"qualityChange":0.03}]},{"groupId":8,"group":"Предметы роскоши","groupName":"luxury","turnover":4790000000,"turnoverChange":0.204,"share":0.0756,"margin":1.44,"competition":4,"priceLevel":31.77,"products":[{"productId":437,"product":"Арома-палочки","productName":"aroma","volume":317710000,"volumeChange":0.151,"amount":268124,"amountChange":0.14400000000000002,"priceLevel":26.08,"sellers":23,"sellersChange":-2,"divisions":135,"divisionsChange":-11,"competition":3,"price":1191,"priceChange":12.42,"quality":5.96,"qualityChange":0.03},{"productId":209,"product":"Белье","productName":"underwear","volume":292760000,"volumeChange":0.13,"amount":138122,"amountChange":0.11900000000000001,"priceLevel":21.48,"sellers":25,"sellersChange":0,"divisions":147,"divisionsChange":-3,"competition":4,"price":2124,"priceChange":16.28,"quality":5.19,"qualityChange":0},{"productId":321,"product":"Бижутерия","productName":"bijouterie","volume":262160000.00000003,"volumeChange":0.152,"amount":104483,"amountChange":0.161,"priceLevel":22.29,"sellers":24,"sellersChange":0,"divisions":131,"divisionsChange":1,"competition":3,"price":2498,"priceChange":-22.65,"quality":5.98,"qualityChange":0},{"productId":325,"product":"Бритва","productName":"razor","volume":390450000,"volumeChange":0.253,"amount":66392,"amountChange":0.24,"priceLevel":26.49,"sellers":24,"sellersChange":-1,"divisions":143,"divisionsChange":-4,"competition":4,"price":5909,"priceChange":73.14,"quality":5.78,"qualityChange":0.04},{"productId":152,"product":"Золотые часы","productName":"watches","volume":421920000,"volumeChange":0.285,"amount":1823,"amountChange":0.289,"priceLevel":48.32,"sellers":24,"sellersChange":-1,"divisions":133,"divisionsChange":-4,"competition":3,"price":231680,"priceChange":367.69,"quality":5.95,"qualityChange":-0.01},{"productId":405,"product":"Колготки","productName":"tights","volume":266630000,"volumeChange":0.185,"amount":143577,"amountChange":0.183,"priceLevel":30.87,"sellers":25,"sellersChange":2,"divisions":130,"divisionsChange":6,"competition":4,"price":1846,"priceChange":-4.79,"quality":5.39,"qualityChange":0},{"productId":382,"product":"Косметика","productName":"makeup","volume":209610000,"volumeChange":0.08199999999999999,"amount":198130,"amountChange":0.08199999999999999,"priceLevel":0,"sellers":27,"sellersChange":1,"divisions":150,"divisionsChange":1,"competition":4,"price":1059,"priceChange":6.14,"quality":5.51,"qualityChange":0.06},{"productId":438,"product":"Массажер","productName":"massager","volume":338110000,"volumeChange":0.2,"amount":10115,"amountChange":0.201,"priceLevel":24.78,"sellers":23,"sellersChange":0,"divisions":130,"divisionsChange":0,"competition":4,"price":33523,"priceChange":105,"quality":5.51,"qualityChange":0.05},{"productId":170,"product":"Парфюмерия","productName":"parfume","volume":253690000,"volumeChange":0.172,"amount":19024,"amountChange":0.171,"priceLevel":29.51,"sellers":25,"sellersChange":1,"divisions":143,"divisionsChange":4,"competition":4,"price":13324,"priceChange":-9.18,"quality":5.74,"qualityChange":-0.03},{"productId":347,"product":"Сувенир","productName":"souvenir","volume":463180000,"volumeChange":0.295,"amount":36597,"amountChange":0.303,"priceLevel":37.03,"sellers":26,"sellersChange":0,"divisions":148,"divisionsChange":-2,"competition":3,"price":12609,"priceChange":-93.42,"quality":6.05,"qualityChange":-0.03},{"productId":147,"product":"Сумка","productName":"bag","volume":260959999.99999997,"volumeChange":0.21600000000000003,"amount":20819,"amountChange":0.21100000000000002,"priceLevel":9.25,"sellers":22,"sellersChange":0,"divisions":124,"divisionsChange":0,"competition":3,"price":12592,"priceChange":84.32,"quality":5.45,"qualityChange":0.04},{"productId":403,"product":"Фен","productName":"hairdryer","volume":333370000,"volumeChange":0.175,"amount":61706,"amountChange":0.175,"priceLevel":15.36,"sellers":23,"sellersChange":0,"divisions":144,"divisionsChange":0,"competition":4,"price":5397,"priceChange":-4.68,"quality":5.67,"qualityChange":0.01},{"productId":402,"product":"Цветы","productName":"flowers","volume":229320000,"volumeChange":0.124,"amount":198864,"amountChange":0.122,"priceLevel":39.55,"sellers":22,"sellersChange":-1,"divisions":137,"divisionsChange":-8,"competition":3,"price":1155,"priceChange":3.98,"quality":7.45,"qualityChange":0.02},{"productId":404,"product":"Эпилятор","productName":"epilator","volume":283550000,"volumeChange":0.153,"amount":92584,"amountChange":0.17300000000000001,"priceLevel":11.1,"sellers":22,"sellersChange":2,"divisions":141,"divisionsChange":12,"competition":3,"price":3067,"priceChange":-6.73,"quality":5.8,"qualityChange":-0.04},{"productId":166,"product":"Ювелирные украшения","productName":"jewelry","volume":468550000,"volumeChange":0.317,"amount":1777,"amountChange":0.313,"priceLevel":85.55,"sellers":24,"sellersChange":-1,"divisions":128,"divisionsChange":-4,"competition":3,"price":263553,"priceChange":270.47,"quality":5.69,"qualityChange":-0.01}]},{"groupId":11,"group":"Рестораны","groupName":"restaurant","turnover":4120000000,"turnoverChange":0.13699999999999998,"share":0.065,"margin":0,"competition":4,"priceLevel":53.43,"products":[{"productId":275,"product":"Борщ","productName":"borcht","volume":60630000,"volumeChange":0.237,"amount":793219,"amountChange":0.22699999999999998,"priceLevel":31.09,"sellers":17,"sellersChange":3,"divisions":115,"divisionsChange":18,"competition":2,"price":76.75,"priceChange":0.25,"quality":6.32,"qualityChange":0.02},{"productId":294,"product":"Винегрет","productName":"venigret","volume":120330000,"volumeChange":0.11800000000000001,"amount":1556992,"amountChange":0.121,"priceLevel":41.16,"sellers":22,"sellersChange":4,"divisions":120,"divisionsChange":12,"competition":2,"price":77.23,"priceChange":-0.47,"quality":6.46,"qualityChange":0.06},{"productId":296,"product":"Гамбургер","productName":"hamburger","volume":257089999.99999997,"volumeChange":0.16,"amount":426785,"amountChange":0.153,"priceLevel":60.05,"sellers":38,"sellersChange":0,"divisions":251,"divisionsChange":0,"competition":3,"price":604,"priceChange":4.11,"quality":5.98,"qualityChange":0.02},{"productId":392,"product":"Глинтвейн","productName":"alkococteil","volume":88970000,"volumeChange":0.095,"amount":102941,"amountChange":0.099,"priceLevel":25.22,"sellers":24,"sellersChange":-1,"divisions":146,"divisionsChange":-8,"competition":2,"price":861,"priceChange":-5.46,"quality":6.4,"qualityChange":0.05},{"productId":286,"product":"Жареная рыба","productName":"friedfish","volume":225730000,"volumeChange":0.152,"amount":210689,"amountChange":0.147,"priceLevel":57.75,"sellers":30,"sellersChange":1,"divisions":180,"divisionsChange":2,"competition":3,"price":1071,"priceChange":5.93,"quality":5.94,"qualityChange":0.02},{"productId":389,"product":"Запеканка","productName":"frenchfries","volume":258790000.00000003,"volumeChange":0.121,"amount":786780,"amountChange":0.11800000000000001,"priceLevel":53.98,"sellers":35,"sellersChange":3,"divisions":176,"divisionsChange":6,"competition":4,"price":331,"priceChange":0.89,"quality":6.12,"qualityChange":0.11},{"productId":385,"product":"Итальянское ассорти","productName":"potatomeat","volume":255440000,"volumeChange":0.17,"amount":223682,"amountChange":0.16699999999999998,"priceLevel":47.66,"sellers":31,"sellersChange":0,"divisions":231,"divisionsChange":0,"competition":3,"price":1143,"priceChange":1.7,"quality":6.19,"qualityChange":0.05},{"productId":393,"product":"Молочный коктейль","productName":"juicecocteil","volume":136960000,"volumeChange":0.106,"amount":1071890,"amountChange":0.109,"priceLevel":28.25,"sellers":31,"sellersChange":0,"divisions":143,"divisionsChange":8,"competition":2,"price":127,"priceChange":-0.84,"quality":6.16,"qualityChange":0},{"productId":283,"product":"Мясо по-французски","productName":"frenchmeat","volume":269350000,"volumeChange":0.166,"amount":142278,"amountChange":0.163,"priceLevel":64.08,"sellers":36,"sellersChange":0,"divisions":261,"divisionsChange":1,"competition":4,"price":1894,"priceChange":7.75,"quality":5.82,"qualityChange":0.02},{"productId":390,"product":"Пивной сет","productName":"nuggets","volume":223220000,"volumeChange":0.136,"amount":135727,"amountChange":0.13,"priceLevel":52.8,"sellers":36,"sellersChange":1,"divisions":209,"divisionsChange":8,"competition":4,"price":1648,"priceChange":13.1,"quality":5.79,"qualityChange":0.03},{"productId":298,"product":"Пицца","productName":"pizza","volume":250710000,"volumeChange":0.154,"amount":327619,"amountChange":0.15,"priceLevel":57.08,"sellers":36,"sellersChange":0,"divisions":243,"divisionsChange":0,"competition":3,"price":767,"priceChange":4.28,"quality":6.11,"qualityChange":0.03},{"productId":284,"product":"Плов","productName":"pilaf","volume":157450000,"volumeChange":0.109,"amount":335156,"amountChange":0.105,"priceLevel":68.43,"sellers":19,"sellersChange":0,"divisions":120,"divisionsChange":0,"competition":2,"price":470,"priceChange":1.66,"quality":5.9,"qualityChange":0.03},{"productId":386,"product":"Ребрышки по-фламандски","productName":"ase","volume":253780000,"volumeChange":0.17,"amount":558693,"amountChange":0.17,"priceLevel":64.74,"sellers":28,"sellersChange":0,"divisions":191,"divisionsChange":1,"competition":4,"price":454,"priceChange":0.2,"quality":5.75,"qualityChange":0},{"productId":293,"product":"Салат Греческий","productName":"saladgreece","volume":234110000,"volumeChange":0.135,"amount":380679,"amountChange":0.13,"priceLevel":48.01,"sellers":34,"sellersChange":0,"divisions":240,"divisionsChange":0,"competition":4,"price":615,"priceChange":1.56,"quality":6.98,"qualityChange":0.02},{"productId":290,"product":"Салат Столичный","productName":"saladcapital","volume":174500000,"volumeChange":0.035,"amount":681277,"amountChange":0.033,"priceLevel":36.53,"sellers":31,"sellersChange":-2,"divisions":199,"divisionsChange":-24,"competition":4,"price":255,"priceChange":0.38,"quality":6.17,"qualityChange":0},{"productId":388,"product":"Сельдь под шубой","productName":"saladceasar","volume":240120000,"volumeChange":0.182,"amount":276311,"amountChange":0.17600000000000002,"priceLevel":68.8,"sellers":25,"sellersChange":0,"divisions":132,"divisionsChange":-1,"competition":3,"price":867,"priceChange":3.1,"quality":5.99,"qualityChange":0.04},{"productId":391,"product":"Сидр","productName":"compote","volume":246210000,"volumeChange":0.155,"amount":476491,"amountChange":0.158,"priceLevel":59.19,"sellers":24,"sellersChange":-2,"divisions":174,"divisionsChange":-8,"competition":4,"price":511,"priceChange":-4.14,"quality":6.39,"qualityChange":0.09},{"productId":276,"product":"Солянка","productName":"saltwort","volume":267079999.99999997,"volumeChange":0.172,"amount":428787,"amountChange":0.168,"priceLevel":53.99,"sellers":39,"sellersChange":1,"divisions":290,"divisionsChange":7,"competition":6,"price":624,"priceChange":1.48,"quality":6.16,"qualityChange":0.01},{"productId":302,"product":"Шаурма","productName":"shawarma","volume":242190000,"volumeChange":0.09699999999999999,"amount":764720,"amountChange":0.098,"priceLevel":48.64,"sellers":30,"sellersChange":-4,"divisions":237,"divisionsChange":-33,"competition":4,"price":315,"priceChange":-0.6,"quality":6.73,"qualityChange":-0.02},{"productId":387,"product":"Штрудель","productName":"schnitzel","volume":156200000,"volumeChange":0.028999999999999998,"amount":1425056,"amountChange":0.032,"priceLevel":45.1,"sellers":28,"sellersChange":1,"divisions":148,"divisionsChange":11,"competition":3,"price":109,"priceChange":-0.42,"quality":6.08,"qualityChange":0.04}]}],"date":1723954619259}